Workbook

Sheet OCUPAÇÃO VEICULOS Att Fev 26
A1: ATUALIZAÇÃO QUANDO HOUVER ALTERAÇÃO
A2: ROTA | B2: VEÍCULO | C2: CAPACIDADE | D2: OCUPAÇÃO UTILIZADA | E2: VAGAS DISPONIVEIS | F2: % OCUPAÇÃO DISPONÍVEL | G2: TEMPO DE ROTA | H2: DISTÂNCIA IDA E VOLTA (KM) | I2: HORÁRIO DE CHEGADA FÁBRICA | J2: HORÁRIO SAÍDA FÁBRICA
C3: 1ºTURNO
A4: 1 | B4: {=_xlfn.IFS(C4=15,"VAN",C4=4,"CARRO PEQUENO",C4=6,"SPIN")} -> CARRO PEQUENO | C4: 4 | D4: 4 | E4: =C4-D4 -> 0 | F4: =E4/C4 -> 0 | G4: 0.024305556 | H4: 42 | I4: 0.23958333 | J4: 0.60416667
A5: 2 | B5: {=_xlfn.IFS(C5=15,"VAN",C5=4,"CARRO PEQUENO",C5=6,"SPIN")} -> CARRO PEQUENO | C5: 4 | D5: 1 | E5: =C5-D5 -> 3 | F5: =E5/C5 -> 0.75 | G5: 0.03125 | H5: 84 | I5: 0.23958333 | J5: 0.60416667
A6: 3 | B6: {=_xlfn.IFS(C6=15,"VAN",C6=4,"CARRO PEQUENO",C6=6,"SPIN")} -> VAN | C6: 15 | D6: 7 | E6: =C6-D6 -> 8 | F6: =E6/C6 -> 0.53333333 | G6: 0.046527778 | H6: 90 | I6: 0.23958333 | J6: 0.60416667
A7: 4 | B7: {=_xlfn.IFS(C7=15,"VAN",C7=4,"CARRO PEQUENO",C7=6,"SPIN")} -> VAN | C7: 15 | D7: 7 | E7: =C7-D7 -> 8 | F7: =E7/C7 -> 0.53333333 | G7: 0.052083333 | H7: 100 | I7: 0.23958333 | J7: 0.60416667
A8: 5 | B8: {=_xlfn.IFS(C8=15,"VAN",C8=4,"CARRO PEQUENO",C8=6,"SPIN")} -> VAN | C8: 15 | D8: 8 | E8: =C8-D8 -> 7 | F8: =E8/C8 -> 0.46666667 | G8: 0.041666667 | H8: 104 | I8: 0.23958333 | J8: 0.60416667
A9: 6 | B9: {=_xlfn.IFS(C9=15,"VAN",C9=4,"CARRO PEQUENO",C9=6,"SPIN")} -> VAN | C9: 15 | D9: 10 | E9: =C9-D9 -> 5 | F9: =E9/C9 -> 0.33333333 | G9: 0.052083333 | H9: 118 | I9: 0.23958333 | J9: 0.60416667
A10: 7 | B10: {=_xlfn.IFS(C10=15,"VAN",C10=4,"CARRO PEQUENO",C10=6,"SPIN")} -> CARRO PEQUENO | C10: 4 | D10: 3 | E10: =C10-D10 -> 1 | F10: =E10/C10 -> 0.25 | G10: 0.03125 | H10: 88 | I10: 0.23958333 | J10: 0.60416667
A11: 8 | B11: {=_xlfn.IFS(C11=15,"VAN",C11=4,"CARRO PEQUENO",C11=6,"SPIN")} -> VAN | C11: 15 | D11: 11 | E11: =C11-D11 -> 4 | F11: =E11/C11 -> 0.26666667 | G11: 0.055555556 | H11: 110 | I11: 0.23958333 | J11: 0.60416667
A12: 9 | B12: {=_xlfn.IFS(C12=15,"VAN",C12=4,"CARRO PEQUENO",C12=6,"SPIN")} -> CARRO PEQUENO | C12: 4 | D12: 2 | E12: =C12-D12 -> 2 | F12: =E12/C12 -> 0.5 | G12: 0.025694444 | H12: 88 | I12: 0.23958333 | J12: 0.60416667
A13: 10 | B13: {=_xlfn.IFS(C13=15,"VAN",C13=4,"CARRO PEQUENO",C13=6,"SPIN")} -> CARRO PEQUENO | C13: 4 | D13: 3 | E13: =C13-D13 -> 1 | F13: =E13/C13 -> 0.25 | G13: 0.052083333 | H13: 80 | I13: 0.23958333 | J13: 0.60416667
A14: TOTAL | C14: =SUM(C4:C13) -> 95 | D14: =SUM(D4:D13) -> 56 | E14: =SUM(E4:E13) -> 39 | F14: =E14/C14 -> 0.41052632 | G14: =AVERAGE(G4:G13) -> 0.04125 | H14: =SUM(H4:H13) -> 904
A16: ROTA | B16: VEÍCULO | C16: CAPACIDADE | D16: OCUPAÇÃO UTILIZADA | E16: VAGAS DISPONIVEIS | F16: % OCUPAÇÃO DISPONÍVEL | G16: TEMPO DE ROTA | H16: DISTÂNCIA IDA E VOLTA (KM) | I16: HORÁRIO DE CHEGADA FÁBRICA | J16: HORÁRIO SAÍDA FÁBRICA
C17: ADM
A18: 1 | B18: {=_xlfn.IFS(C18=15,"VAN",C18=4,"CARRO PEQUENO",C18=6,"SPIN")} -> CARRO PEQUENO | C18: 4 | D18: 4 | E18: =C18-D18 -> 0 | F18: =E18/C18 -> 0 | G18: 0.03125 | H18: 56 | I18: 0.30208333 | J18: 0.72083333
A19: 2 | B19: {=_xlfn.IFS(C19=15,"VAN",C19=4,"CARRO PEQUENO",C19=6,"SPIN")} -> CARRO PEQUENO | C19: 4 | D19: 4 | E19: =C19-D19 -> 0 | F19: =E19/C19 -> 0 | G19: 0.03125 | H19: 90 | I19: 0.30208333 | J19: 0.72083333
A20: 3 | B20: {=_xlfn.IFS(C20=15,"VAN",C20=4,"CARRO PEQUENO",C20=6,"SPIN")} -> CARRO PEQUENO | C20: 4 | D20: 3 | E20: =C20-D20 -> 1 | F20: =E20/C20 -> 0.25 | G20: 0.034722222 | H20: 62 | I20: 0.30208333 | J20: 0.72083333
A21: 4 | B21: {=_xlfn.IFS(C21=15,"VAN",C21=4,"CARRO PEQUENO",C21=6,"SPIN")} -> CARRO PEQUENO | C21: 4 | D21: 3 | E21: =C21-D21 -> 1 | F21: =E21/C21 -> 0.25 | G21: 0.022916667 | H21: 60 | I21: 0.30208333 | J21: 0.72083333
A22: 5 | B22: {=_xlfn.IFS(C22=15,"VAN",C22=4,"CARRO PEQUENO",C22=6,"SPIN")} -> CARRO PEQUENO | C22: 4 | D22: 4 | E22: =C22-D22 -> 0 | F22: =E22/C22 -> 0 | G22: 0.038194444 | H22: 64 | I22: 0.30208333 | J22: 0.72083333
A23: 6 | B23: {=_xlfn.IFS(C23=15,"VAN",C23=4,"CARRO PEQUENO",C23=6,"SPIN")} -> CARRO PEQUENO | C23: 4 | D23: 1 | E23: =C23-D23 -> 3 | F23: =E23/C23 -> 0.75 | G23: 0.024305556 | H23: 84 | I23: 0.30208333 | J23: 0.72083333
A24: 7 | B24: {=_xlfn.IFS(C24=15,"VAN",C24=4,"CARRO PEQUENO",C24=6,"SPIN")} -> CARRO PEQUENO | C24: 4 | D24: 2 | E24: =C24-D24 -> 2 | F24: =E24/C24 -> 0.5 | G24: 0.0069444444 | H24: 30 | I24: 0.30208333 | J24: 0.72083333
A25: 8 | B25: {=_xlfn.IFS(C25=15,"VAN",C25=4,"CARRO PEQUENO",C25=6,"SPIN")} -> CARRO PEQUENO | C25: 4 | D25: 2 | E25: =C25-D25 -> 2 | F25: =E25/C25 -> 0.5 | G25: 0.017361111 | H25: 66 | I25: 0.30208333 | J25: 0.72083333
A26: TOTAL | C26: =SUM(C18:C25) -> 32 | D26: =SUM(D18:D25) -> 23 | E26: =SUM(E18:E25) -> 9 | F26: =E26/C26 -> 0.28125 | G26: =AVERAGE(G18:G25) -> 0.025868056 | H26: =SUM(H18:H25) -> 512
A28: ROTA | B28: VEÍCULO | C28: CAPACIDADE | D28: OCUPAÇÃO UTILIZADA | E28: VAGAS DISPONIVEIS | F28: % OCUPAÇÃO DISPONÍVEL | G28: TEMPO DE ROTA | H28: DISTÂNCIA IDA E VOLTA (KM) | I28: HORÁRIO DE CHEGADA FÁBRICA | J28: HORÁRIO SAÍDA FÁBRICA
C29: 2° TURNO
A30: 1 | B30: {=_xlfn.IFS(C30=15,"VAN",C30=4,"CARRO PEQUENO",C30=6,"SPIN")} -> VAN | C30: 15 | D30: 8 | E30: =C30-D30 -> 7 | F30: =E30/C30 -> 0.46666667 | G30: 0.048611111 | H30: 112 | I30: 0.58680556 | J30: 0.94791667
A31: 2 | B31: {=_xlfn.IFS(C31=15,"VAN",C31=4,"CARRO PEQUENO",C31=6,"SPIN")} -> VAN | C31: 15 | D31: 8 | E31: =C31-D31 -> 7 | F31: =E31/C31 -> 0.46666667 | G31: 0.052083333 | H31: 100 | I31: 0.58680556 | J31: 0.94791667
A32: 3 | B32: {=_xlfn.IFS(C32=15,"VAN",C32=4,"CARRO PEQUENO",C32=6,"SPIN")} -> VAN | C32: 15 | D32: 6 | E32: =C32-D32 -> 9 | F32: =E32/C32 -> 0.6 | G32: 0.047916667 | H32: 82 | I32: 0.58680556 | J32: 0.94791667
A33: 4 | B33: {=_xlfn.IFS(C33=15,"VAN",C33=4,"CARRO PEQUENO",C33=6,"SPIN")} -> SPIN | C33: 6 | D33: 5 | E33: =C33-D33 -> 1 | F33: =E33/C33 -> 0.16666667 | G33: 0.04375 | H33: 100 | I33: 0.58680556 | J33: 0.94791667
A34: 5 | B34: {=_xlfn.IFS(C34=15,"VAN",C34=4,"CARRO PEQUENO",C34=6,"SPIN")} -> SPIN | C34: 6 | D34: 5 | E34: =C34-D34 -> 1 | F34: =E34/C34 -> 0.16666667 | G34: 0.045138889 | H34: 90 | I34: 0.58680556 | J34: 0.94791667
A35: TOTAL | C35: =SUM(C30:C34) -> 57 | D35: =SUM(D30:D34) -> 32 | E35: =SUM(E30:E34) -> 25 | F35: =E35/C35 -> 0.43859649 | G35: =AVERAGE(G30:G34) -> 0.0475 | H35: =SUM(H30:H34) -> 484
A37: ROTA | B37: VEÍCULO | C37: CAPACIDADE | D37: OCUPAÇÃO UTILIZADA | E37: VAGAS DISPONIVEIS | F37: % OCUPAÇÃO DISPONÍVEL | G37: TEMPO DE ROTA | H37: DISTÂNCIA IDA E VOLTA (KM) | I37: HORÁRIO CHEGADA FÁBRICA | J37: HORÁRIO SAÍDA FÁBRICA
C38: 3° TURNO
A39: 1 | B39: {=_xlfn.IFS(C39=15,"VAN",C39=4,"CARRO PEQUENO",C39=6,"SPIN")} -> VAN | C39: 15 | D39: 9 | E39: =C39-D39 -> 6 | F39: =E39/C39 -> 0.4 | G39: 0.03125 | H39: 108 | I39: 0.93055556 | J39: 0.26041667
A40: 2 | B40: {=_xlfn.IFS(C40=15,"VAN",C40=4,"CARRO PEQUENO",C40=6,"SPIN")} -> CARRO PEQUENO | C40: 4 | D40: 2 | E40: =C40-D40 -> 2 | F40: =E40/C40 -> 0.5 | G40: 0.041666667 | H40: 68 | I40: 0.93055556 | J40: 0.26041667
A41: TOTAL | C41: =SUM(C39:C40) -> 19 | D41: =SUM(D39:D40) -> 11 | E41: =SUM(E39:E40) -> 8 | F41: =E41/C41 -> 0.42105263 | G41: =AVERAGE(G39:G40) -> 0.036458333 | H41: =SUM(H39:H40) -> 176

Sheet ATIVOS
A1: Ativo? | B1: EMPRESA/SETOR | C1: GPID | D1: ROTA | E1: TURNO | F1: CARRO | G1: NOME ABREVIADO | H1: NOME COMPLETO | I1: EMPRESA | J1: CC | K1: DATA ADMISSAO | L1: ENDEREÇO COMPLETO | M1: RUA | N1: Nº | O1: BAIRRO | P1: CIDADE | Q1: PONTO DE EMBARQUE | R1: REFERÊNCIA | S1: TELEFONE | T1: DATA ALTERACAO ENDERECO
A2: SIM | C2: =_xlfn.XLOOKUP(H2,RH!$D$2:$D$116,RH!$C$2:$C$116,"Terceiro") -> 40192586 | D2: =E2&" - "&F2 -> 1T - ROTA/5 | E2: 1T | F2: ROTA/5 | G2: ACACIO. C | H2: ACACIO LUIZ LIMA CORREIA | I2: PEPSICO | J2: =_xlfn.XLOOKUP(H2,RH!$D$2:$D$116,RH!$K$2:$K$116,"Terceiro") -> BR1A294 | K2: 41102 | L2: =M2 & ", " & N2 & ", " & O2 & ", " & P2 & ", BAHIA" & ", BRASIL" -> R. FELIX PACHECO, 259, PANORAMA, FEIRA DE SANTANA, BAHIA, BRASIL | M2: R. FELIX PACHECO | N2: 259 | O2: PANORAMA | P2: FEIRA DE SANTANA | Q2: R. FELIX PACHECO N° 259 - RUA EM FRENTE AO PORTAL DESCARGA DE G BARBOSA | R2: RUA EM FRENTE AO PORTAL DESCARGA DE G BARBOSA
A3: SIM | C3: =_xlfn.XLOOKUP(H3,RH!$D$2:$D$116,RH!$C$2:$C$116,"Terceiro") -> 40285860 | D3: =E3&" - "&F3 -> 1T - ROTA/6 | E3: 1T | F3: ROTA/6 | G3: ADEMILDES | H3: ADEMILDES DA CONCEICAO | I3: PEPSICO | J3: =_xlfn.XLOOKUP(H3,RH!$D$2:$D$116,RH!$K$2:$K$116,"Terceiro") -> BR1A009 | K3: 41925 | L3: =M3 & ", " & N3 & ", " & O3 & ", " & P3 & ", BAHIA" & ", BRASIL" -> RUA RIO VERDE, 55, CONCEIÇÃO II, FEIRA DE SANTANA, BAHIA, BRASIL | M3: RUA RIO VERDE | N3: 55 | O3: CONCEIÇÃO II | P3: FEIRA DE SANTANA | Q3: RUA RIO VERDE 55 - EM FRENTE AO SALÃO NINA CABELELEIRO | R3: EM FRENTE AO SALÃO NINA CABELELEIRO
A4: SIM | C4: =_xlfn.XLOOKUP(H4,RH!$D$2:$D$116,RH!$C$2:$C$116,"Terceiro") -> 80997371 | D4: =E4&" - "&F4 -> 2T - ROTA/1 | E4: 2T | F4: ROTA/1 | G4: ADRIANO. F | H4: ADRIANO MACHADO FERREIRA | I4: PEPSICO | J4: =_xlfn.XLOOKUP(H4,RH!$D$2:$D$116,RH!$K$2:$K$116,"Terceiro") -> BR1A312 | K4: 44872 | L4: =M4 & ", " & N4 & ", " & O4 & ", " & P4 & ", BAHIA" & ", BRASIL" -> RUA AMADO BAHIA, N/A, PANORAMA, FEIRA DE SANTANA, BAHIA, BRASIL | M4: RUA AMADO BAHIA | N4: N/A | O4: PANORAMA | P4: FEIRA DE SANTANA | Q4: RUA AMADO BAHIA EM FRENTE A IGREJA DAS TESTEMUNHAS DE JEOVÁ | R4: IGREJA DAS TESTEMUNHAS DE JEOVÁ
A5: SIM | C5: =_xlfn.XLOOKUP(H5,RH!$D$2:$D$116,RH!$C$2:$C$116,"Terceiro") -> 40205767 | D5: =E5&" - "&F5 -> 3T - ROTA/1 | E5: 3T | F5: ROTA/1 | G5: Adriano. M | H5: ADRIANO DOS SANTOS MORAIS | I5: PEPSICO | J5: =_xlfn.XLOOKUP(H5,RH!$D$2:$D$116,RH!$K$2:$K$116,"Terceiro") -> BR1A312 | K5: 44872 | L5: =M5 & ", " & N5 & ", " & O5 & ", " & P5 & ", BAHIA" & ", BRASIL" -> ESCOLA TEREZA CUNHA , N/A, CALUMBI, FEIRA DE SANTANA, BAHIA, BRASIL | M5: ESCOLA TEREZA CUNHA | N5: N/A | O5: CALUMBI | P5: FEIRA DE SANTANA | Q5: Ao lado da Escola Tereza Cunha | R5: Ao lado da Escola Tereza Cunha
A6: SIM | C6: =_xlfn.XLOOKUP(H6,RH!$D$2:$D$116,RH!$C$2:$C$116,"Terceiro") -> 80315521 | D6: =E6&" - "&F6 -> ADM - ROTA/8 | E6: ADM | F6: ROTA/8 | G6: ALCIDES J | H6: ALCIDES BARBOSA DE SOUSA JUNIOR | I6: PEPSICO | J6: =_xlfn.XLOOKUP(H6,RH!$D$2:$D$116,RH!$K$2:$K$116,"Terceiro") -> BR1A294 | K6: 44242 | L6: =M6 & ", " & N6 & ", " & O6 & ", " & P6 & ", BAHIA" & ", BRASIL" -> RUA B, 41, AVIARIO, FEIRA DE SANTANA, BAHIA, BRASIL | M6: RUA B | N6: 41 | O6: AVIARIO | P6: FEIRA DE SANTANA | Q6: RUA B N°41 PONTO DE APANHA EM FRENTE A IGREJA CATOLICA | R6: IGREJA CATOLICA
A7: SIM | C7: =_xlfn.XLOOKUP(H7,RH!$D$2:$D$116,RH!$C$2:$C$116,"Terceiro") -> 80069277 | D7: =E7&" - "&F7 -> 1T - ROTA/3 | E7: 1T | F7: ROTA/3 | G7: ALEXANDRE. J | H7: ALEXANDRE SOUZA DE JESUS | I7: PEPSICO | J7: =_xlfn.XLOOKUP(H7,RH!$D$2:$D$116,RH!$K$2:$K$116,"Terceiro") -> BR1A294 | K7: 42933 | L7: =M7 & ", " & N7 & ", " & O7 & ", " & P7 & ", BAHIA" & ", BRASIL" -> RUA TUIUCA, N/A, JOÃO PAULO, FEIRA DE SANTANA, BAHIA, BRASIL | M7: RUA TUIUCA | N7: N/A | O7: JOÃO PAULO | P7: FEIRA DE SANTANA | Q7: RUA TIJUCA - EM FRENTE A PIZZARIA LAPETITOSA | R7: EM FRENTE A PIZZARIA LAPETITOSA
A8: SIM | C8: =_xlfn.XLOOKUP(H8,RH!$D$2:$D$116,RH!$C$2:$C$116,"Terceiro") -> Terceiro | D8: =E8&" - "&F8 -> 1T - ROTA/4 | E8: 1T | F8: ROTA/4 | G8: ANA PAULA DA S. | H8: ANA PAULA DA SILVA BRITO | I8: LIMGER | J8: BR4A006 | K8: 45665 | L8: =M8 & ", " & N8 & ", " & O8 & ", " & P8 & ", BAHIA" & ", BRASIL" -> RUA MANTIQUEIRA, 455, RUA NOVA, FEIRA DE SANTANA, BAHIA, BRASIL | M8: RUA MANTIQUEIRA | N8: 455 | O8: RUA NOVA | P8: FEIRA DE SANTANA | Q8: RUA MANTIQUEIRA, 455, PROX. AO CRAS | R8: PROX. AO CRAS
A9: SIM | C9: =_xlfn.XLOOKUP(H9,RH!$D$2:$D$116,RH!$C$2:$C$116,"Terceiro") -> 80038367 | D9: =E9&" - "&F9 -> ADM - ROTA/1 | E9: ADM | F9: ROTA/1 | G9: ANAILDE. C | H9: ANAILDE CRUZ ATAIDE CARVALHO | I9: PEPSICO | J9: =_xlfn.XLOOKUP(H9,RH!$D$2:$D$116,RH!$K$2:$K$116,"Terceiro") -> BR5A003 | K9: 42737 | L9: =M9 & ", " & N9 & ", " & O9 & ", " & P9 & ", BAHIA" & ", BRASIL" -> Avenida Artêmia Pires, 8147, Sim, FEIRA DE SANTANA, BAHIA, BRASIL | M9: Avenida Artêmia Pires | N9: 8147 | O9: Sim | P9: FEIRA DE SANTANA | Q9: COND. PARQUE FLORA | R9: COND. PARQUE FLORA
A10: SIM | C10: =_xlfn.XLOOKUP(H10,RH!$D$2:$D$116,RH!$C$2:$C$116,"Terceiro") -> 40172746 | D10: =E10&" - "&F10 -> ADM - ROTA/4 | E10: ADM | F10: ROTA/4 | G10: ANDERSON A. | H10: ANDERSON DE JESUS AMARAL | I10: PEPSICO | J10: =_xlfn.XLOOKUP(H10,RH!$D$2:$D$116,RH!$K$2:$K$116,"Terceiro") -> BR1A004 | K10: 40665 | L10: =M10 & ", " & N10 & ", " & O10 & ", " & P10 & ", BAHIA" & ", BRASIL" -> RUA SENADOR QUINTINO, N/A, SERRARIA BRASIL, FEIRA DE SANTANA, BAHIA, BRASIL | M10: RUA SENADOR QUINTINO | N10: N/A | O10: SERRARIA BRASIL | P10: FEIRA DE SANTANA | Q10: RUA SENADOR QUINTINO | R10: PRAÇA DA PAQUERA
A11: SIM | C11: =_xlfn.XLOOKUP(H11,RH!$D$2:$D$116,RH!$C$2:$C$116,"Terceiro") -> 81009737 | D11: =E11&" - "&F11 -> 2T - ROTA/2 | E11: 2T | F11: ROTA/2 | G11: ANDERSON. V | H11: ANDERSON FELIPE VENTURA DA SILVA | I11: PEPSICO | J11: =_xlfn.XLOOKUP(H11,RH!$D$2:$D$116,RH!$K$2:$K$116,"Terceiro") -> BR1A002 | K11: 44928 | L11: =M11 & ", " & N11 & ", " & O11 & ", " & P11 & ", BAHIA" & ", BRASIL" -> RUA VITORINO FREIRE, 822, MANGABEIRA, FEIRA DE SANTANA, BAHIA, BRASIL | M11: RUA VITORINO FREIRE | N11: 822 | O11: MANGABEIRA | P11: FEIRA DE SANTANA | Q11: RUA VITORINO FREIRE, Nº 822 EM FRENTE AO COND: BERGAMO | R11: COND: BERGAMO
A12: SIM | C12: =_xlfn.XLOOKUP(H12,RH!$D$2:$D$116,RH!$C$2:$C$116,"Terceiro") -> 80069273 | D12: =E12&" - "&F12 -> 2T - ROTA/3 | E12: 2T | F12: ROTA/3 | G12: ATAIDE. M | H12: ATAIDE DE MATOS SANTANA | I12: PEPSICO | J12: =_xlfn.XLOOKUP(H12,RH!$D$2:$D$116,RH!$K$2:$K$116,"Terceiro") -> BR1A312 | K12: 42933 | L12: =M12 & ", " & N12 & ", " & O12 & ", " & P12 & ", BAHIA" & ", BRASIL" -> AV. SANTO ANDRE, N/A, CASEB, FEIRA DE SANTANA, BAHIA, BRASIL | M12: AV. SANTO ANDRE | N12: N/A | O12: CASEB | P12: FEIRA DE SANTANA | Q12: AV. SANTO ANDRE EM FRENTE AO COND: DOM RESIDENCIAL | R12: COND: DOM RESIDENCIAL
A13: SIM | C13: =_xlfn.XLOOKUP(H13,RH!$D$2:$D$116,RH!$C$2:$C$116,"Terceiro") -> Terceiro | D13: =E13&" - "&F13 -> 1T - ROTA/8 | E13: 1T | F13: ROTA/8 | G13: CARLOS ALBERTO G. | H13: CARLOS ALBERTO GONÇALVES QUEIROZ | I13: LIMGER | J13: BR4A006 | K13: 45665 | L13: =M13 & ", " & N13 & ", " & O13 & ", " & P13 & ", BAHIA" & ", BRASIL" -> RUA DIVAL MACHADO, 18, GABRIELA, FEIRA DE SANTANA, BAHIA, BRASIL | M13: RUA DIVAL MACHADO | N13: 18 | O13: GABRIELA | P13: FEIRA DE SANTANA | Q13: RUA DIVAL MACHADO, N° 18 | R13: RUA DIVAL MACHADO, N° 18
A14: SIM | C14: =_xlfn.XLOOKUP(H14,RH!$D$2:$D$116,RH!$C$2:$C$116,"Terceiro") -> Terceiro | D14: =E14&" - "&F14 -> ADM - ROTA/5 | E14: ADM | F14: ROTA/5 | G14: CARLOS ANTONIO G. | H14: CARLOS ANTONIO GONÇALVES QUEIROZ | I14: LIMGER | J14: BR4A006 | K14: 45665 | L14: =M14 & ", " & N14 & ", " & O14 & ", " & P14 & ", BAHIA" & ", BRASIL" -> RUA DIVAL MACHADO, 18, GABRIELA, FEIRA DE SANTANA, BAHIA, BRASIL | M14: RUA DIVAL MACHADO | N14: 18 | O14: GABRIELA | P14: FEIRA DE SANTANA | Q14: RUA DIVAL MACHADO
A15: SIM | C15: =_xlfn.XLOOKUP(H15,RH!$D$2:$D$116,RH!$C$2:$C$116,"Terceiro") -> Terceiro | D15: =E15&" - "&F15 -> 2T - ROTA/1 | E15: 2T | F15: ROTA/1 | G15: CLAUDIA MARIA Q. | H15: CLAUDIA MARIA QUEIROZ | I15: LIMGER | J15: BR4A006 | K15: 45665 | L15: =M15 & ", " & N15 & ", " & O15 & ", " & P15 & ", BAHIA" & ", BRASIL" -> RUA EL SALVADOR, 38, FEIRA VII, FEIRA DE SANTANA, BAHIA, BRASIL | M15: RUA EL SALVADOR | N15: 38 | O15: FEIRA VII | P15: FEIRA DE SANTANA | Q15: RUA EL SALVADOR, Nº 38 - CENTRO AUTOMOTIVO ANDERSON CAR | R15: CENTRO AUTOMOTIVO ANDERSON CAR
A16: SIM | C16: =_xlfn.XLOOKUP(H16,RH!$D$2:$D$116,RH!$C$2:$C$116,"Terceiro") -> Terceiro | D16: =E16&" - "&F16 -> ADM - ROTA/2 | E16: ADM | F16: ROTA/2 | G16: CLAUDIO H. | H16: CLAUDIO HENRIQUE LIVEIRA SANTOS | I16: CWBEM | J16: BR5A008 | K16: 44936 | L16: =M16 & ", " & N16 & ", " & O16 & ", " & P16 & ", BAHIA" & ", BRASIL" -> Avenida Gracindo de Freitas Medeiros , N/A, MANGABEIRA, FEIRA DE SANTANA, BAHIA, BRASIL | M16: Avenida Gracindo de Freitas Medeiros | N16: N/A | O16: MANGABEIRA | P16: FEIRA DE SANTANA | Q16: COND. RESIDENCIAL FONTANA | R16: COND. RESIDENCIAL FONTANA
A17: SIM | C17: =_xlfn.XLOOKUP(H17,RH!$D$2:$D$116,RH!$C$2:$C$116,"Terceiro") -> 81226437 | D17: =E17&" - "&F17 -> ADM - ROTA/3 | E17: ADM | F17: ROTA/3 | G17: CLAUDIO R. Q. A. | H17: CLAUDIO HENRIQUE QUEIROZ ALVES | I17: PEPSICO | J17: =_xlfn.XLOOKUP(H17,RH!$D$2:$D$116,RH!$K$2:$K$116,"Terceiro") -> BR1A004 | K17: 45845 | L17: =M17 & ", " & N17 & ", " & O17 & ", " & P17 & ", BAHIA" & ", BRASIL" -> RUA LEÔCIO SANTOS, 115, SANTA MÔNICA, FEIRA DE SANTANA, BAHIA, BRASIL | M17: RUA LEÔCIO SANTOS | N17: 115 | O17: SANTA MÔNICA | P17: FEIRA DE SANTANA | Q17: RUA ATRÁS DA SEABRA HOTEL | R17: ATRÁS DA SEABRA HOTELL
A18: SIM | C18: =_xlfn.XLOOKUP(H18,RH!$D$2:$D$116,RH!$C$2:$C$116,"Terceiro") -> 80888568 | D18: =E18&" - "&F18 -> 2T - ROTA/1 | E18: 2T | F18: ROTA/1 | G18: CLAUDIONOR. C | H18: CLAUDIONOR CERQUEIRA DA COSTA | I18: PEPSICO | J18: =_xlfn.XLOOKUP(H18,RH!$D$2:$D$116,RH!$K$2:$K$116,"Terceiro") -> BR1A007 | K18: 44516 | L18: =M18 & ", " & N18 & ", " & O18 & ", " & P18 & ", BAHIA" & ", BRASIL" -> RUA DO TELEGRAFO, N/A, FRATERNIDADE, FEIRA DE SANTANA, BAHIA, BRASIL | M18: RUA DO TELEGRAFO | N18: N/A | O18: FRATERNIDADE | P18: FEIRA DE SANTANA | Q18: RUA DO TELEGRAFO, PONTO DE APANHA EM FRENTE A IGREJA QUADRANGULAR | R18: IGREJA QUADRANGULAR
A19: SIM | C19: =_xlfn.XLOOKUP(H19,RH!$D$2:$D$116,RH!$C$2:$C$116,"Terceiro") -> 80997603 | D19: =E19&" - "&F19 -> 1T - ROTA/10 | E19: 1T | F19: ROTA/10 | G19: CLEIDIANE. L | H19: CLEIDIANE DE OLIVEIRA LIMA | I19: PEPSICO | J19: =_xlfn.XLOOKUP(H19,RH!$D$2:$D$116,RH!$K$2:$K$116,"Terceiro") -> BR1A010 | K19: 44872 | L19: =M19 & ", " & N19 & ", " & O19 & ", " & P19 & ", BAHIA" & ", BRASIL" -> RUA CORRENTES, 68, CAMPO LIMPO, FEIRA DE SANTANA, BAHIA, BRASIL | M19: RUA CORRENTES | N19: 68 | O19: CAMPO LIMPO | P19: FEIRA DE SANTANA | Q19: RUA CORRENTES, Nº 68, EM FRENTE A MERCEARIA VIDEIRA | R19: EM FRENTE A MERCEARIA VIDEIRA
A20: SIM | C20: =_xlfn.XLOOKUP(H20,RH!$D$2:$D$116,RH!$C$2:$C$116,"Terceiro") -> Terceiro | D20: =E20&" - "&F20 -> 1T - ROTA/6 | E20: 1T | F20: ROTA/6 | G20: CRIS KELLY | H20: CRIS KELLY PEREIRA DA COSTA | I20: CWBEM | J20: BR5A008 | K20: 45869 | L20: =M20 & ", " & N20 & ", " & O20 & ", " & P20 & ", BAHIA" & ", BRASIL" -> RUA MARAÚ, 230, SANTO ANTÔNIO DOS PRAZERES, FEIRA DE SANTANA, BAHIA, BRASIL | M20: RUA MARAÚ | N20: 230 | O20: SANTO ANTÔNIO DOS PRAZERES | P20: FEIRA DE SANTANA | Q20: RUA MARAÚ, Nº 230 - PROX. AO PASTEL DO GALEGO | R20: PROX. AO PASTEL DO GALEGO
A21: SIM | C21: =_xlfn.XLOOKUP(H21,RH!$D$2:$D$116,RH!$C$2:$C$116,"Terceiro") -> 40216111 | D21: =E21&" - "&F21 -> 1T - ROTA/3 | E21: 1T | F21: ROTA/3 | G21: CRISTIANE. A | H21: CRISTIANE SANTOS DE OLIVEIRA ARAUJO | I21: PEPSICO | J21: =_xlfn.XLOOKUP(H21,RH!$D$2:$D$116,RH!$K$2:$K$116,"Terceiro") -> BR1A312 | K21: 41435 | L21: =M21 & ", " & N21 & ", " & O21 & ", " & P21 & ", BAHIA" & ", BRASIL" -> RUA PERIPERI, N/A, QUEIMADINHA, FEIRA DE SANTANA, BAHIA, BRASIL | M21: RUA PERIPERI | N21: N/A | O21: QUEIMADINHA | P21: FEIRA DE SANTANA | Q21: RUA PERIPERI - PROX A ESCOLA DASIS | R21: PROX A ESCOLA DASIS
A22: SIM | C22: =_xlfn.XLOOKUP(H22,RH!$D$2:$D$116,RH!$C$2:$C$116,"Terceiro") -> 81069369 | D22: =E22&" - "&F22 -> 3T - ROTA/1 | E22: 3T | F22: ROTA/1 | G22: Dacio M | H22: DACIO DA CONCEICAO MACHADO | I22: PEPSICO | J22: =_xlfn.XLOOKUP(H22,RH!$D$2:$D$116,RH!$K$2:$K$116,"Terceiro") -> BR1A294 | K22: 45152 | L22: =M22 & ", " & N22 & ", " & O22 & ", " & P22 & ", BAHIA" & ", BRASIL" -> Rua Para, 320, QUEIMADINHA, FEIRA DE SANTANA, BAHIA, BRASIL | M22: Rua Para | N22: 320 | O22: QUEIMADINHA | P22: FEIRA DE SANTANA | Q22: Rua Para, N° 320
A23: SIM | C23: =_xlfn.XLOOKUP(H23,RH!$D$2:$D$116,RH!$C$2:$C$116,"Terceiro") -> 80916371 | D23: =E23&" - "&F23 -> 2T - ROTA/4 | E23: 2T | F23: ROTA/4 | G23: DAIANE. R | H23: DAIANE DE OLIVEIRA RODRIGUES | I23: PEPSICO | J23: =_xlfn.XLOOKUP(H23,RH!$D$2:$D$116,RH!$K$2:$K$116,"Terceiro") -> BR1A312 | K23: 44622 | L23: =M23 & ", " & N23 & ", " & O23 & ", " & P23 & ", BAHIA" & ", BRASIL" -> RUA BREVES, 33, LIMOEIRO, LIMOEIRO, BAHIA, BRASIL | M23: RUA BREVES | N23: 33 | O23: LIMOEIRO | P23: LIMOEIRO | Q23: RUA BREVES, Nº 33, PONTO DE APANHA EM FRENTE A FÁBRICA DE VELAS | R23: FÁBRICA DE VELAS
A24: SIM | C24: =_xlfn.XLOOKUP(H24,RH!$D$2:$D$116,RH!$C$2:$C$116,"Terceiro") -> 80159517 | D24: =E24&" - "&F24 -> ADM - ROTA/1 | E24: ADM | F24: ROTA/1 | G24: DAIANE X. | H24: DAIANE SILVA XAVIER | I24: PEPSICO | J24: =_xlfn.XLOOKUP(H24,RH!$D$2:$D$116,RH!$K$2:$K$116,"Terceiro") -> BR1A002 | K24: 43451 | L24: =M24 & ", " & N24 & ", " & O24 & ", " & P24 & ", BAHIA" & ", BRASIL" -> RUA CAMBORIÚ, 50, Sim, FEIRA DE SANTANA, BAHIA, BRASIL | M24: RUA CAMBORIÚ | N24: 50 | O24: Sim | P24: FEIRA DE SANTANA | Q24: LOCAL DE APANHA EM FRENTE A CAOA CHERY | R24: EM FRENTE A CAOA CHERY
A25: SIM | C25: =_xlfn.XLOOKUP(H25,RH!$D$2:$D$116,RH!$C$2:$C$116,"Terceiro") -> 81145746 | D25: =E25&" - "&F25 -> 2T - ROTA/3 | E25: 2T | F25: ROTA/3 | G25: DERALDO S. | H25: DERALDO DOS SANTOS JUNIOR | I25: PEPSICO | J25: =_xlfn.XLOOKUP(H25,RH!$D$2:$D$116,RH!$K$2:$K$116,"Terceiro") -> BR1A312 | K25: 45425 | L25: =M25 & ", " & N25 & ", " & O25 & ", " & P25 & ", BAHIA" & ", BRASIL" -> RUA CARLOS LADARES, 1058, QUEIMADINHA, FEIRA DE SANTANA, BAHIA, BRASIL | M25: RUA CARLOS LADARES | N25: 1058 | O25: QUEIMADINHA | P25: FEIRA DE SANTANA | Q25: RUA CARLOS LADARES, N°. 1058 - EM FRENTE A CLINICA UNACON | R25: CLINICA UNACON
A26: SIM | C26: =_xlfn.XLOOKUP(H26,RH!$D$2:$D$116,RH!$C$2:$C$116,"Terceiro") -> 80258585 | D26: =E26&" - "&F26 -> 3T - ROTA/1 | E26: 3T | F26: ROTA/1 | G26: Ecio. R | H26: ECIO CONCEICAO DOS REIS | I26: PEPSICO | J26: =_xlfn.XLOOKUP(H26,RH!$D$2:$D$116,RH!$K$2:$K$116,"Terceiro") -> BR1A004 | K26: 43997 | L26: =M26 & ", " & N26 & ", " & O26 & ", " & P26 & ", BAHIA" & ", BRASIL" -> Rua Santos, 101, CASEB, FEIRA DE SANTANA, BAHIA, BRASIL | M26: Rua Santos | N26: 101 | O26: CASEB | P26: FEIRA DE SANTANA | Q26: Rua Santos, N° 101
A27: SIM | C27: =_xlfn.XLOOKUP(H27,RH!$D$2:$D$116,RH!$C$2:$C$116,"Terceiro") -> Terceiro | D27: =E27&" - "&F27 -> 2T - ROTA/1 | E27: 2T | F27: ROTA/1 | G27: EDIPO P. S. | H27: ÉDIPO PINHEIRO SILVA | I27: CWBEM | J27: BR5A008 | K27: 45811 | L27: =M27 & ", " & N27 & ", " & O27 & ", " & P27 & ", BAHIA" & ", BRASIL" -> RUA DOUTOR MACÁRIO CERQUEIRA, 1147, MUCHILA, FEIRA DE SANTANA, BAHIA, BRASIL | M27: RUA DOUTOR MACÁRIO CERQUEIRA | N27: 1147 | O27: MUCHILA | P27: FEIRA DE SANTANA | Q27: RUA DOUTOR MACÁRIO CERQUEIRA, 1147, CONDOMINIO PRINCESA DO SERTÃO | R27: CONDOMINIO PRINCESA DO SERTÃO
A28: SIM | C28: =_xlfn.XLOOKUP(H28,RH!$D$2:$D$116,RH!$C$2:$C$116,"Terceiro") -> 80888181 | D28: =E28&" - "&F28 -> 2T - ROTA/4 | E28: 2T | F28: ROTA/4 | G28: EDMILSON. L | H28: EDMILSON LOPES DE OLIVEIRA | I28: PEPSICO | J28: =_xlfn.XLOOKUP(H28,RH!$D$2:$D$116,RH!$K$2:$K$116,"Terceiro") -> BR1A294 | K28: 44516 | L28: =M28 & ", " & N28 & ", " & O28 & ", " & P28 & ", BAHIA" & ", BRASIL" -> PRAÇA DO LIMOEIRO, N/A, LIMOEIRO, LIMOEIRO, BAHIA, BRASIL | M28: PRAÇA DO LIMOEIRO | N28: N/A | O28: LIMOEIRO | P28: LIMOEIRO | Q28: PRAÇA DO LIMOEIRO, EM FRENTE AO MERCADO MUNICIPAL | R28: MERCADO MUNICIPAL
A29: SIM | C29: =_xlfn.XLOOKUP(H29,RH!$D$2:$D$116,RH!$C$2:$C$116,"Terceiro") -> Terceiro | D29: =E29&" - "&F29 -> 1T - ROTA/8 | E29: 1T | F29: ROTA/8 | G29: EDINEIDE DA S. | H29: EDNEIDE DA SILVA TITO | I29: LIMGER | J29: BR4A006 | K29: 45665 | L29: =M29 & ", " & N29 & ", " & O29 & ", " & P29 & ", BAHIA" & ", BRASIL" -> RUA AEROLINHA ESPANHA, 80, GEORGE AMERICO, FEIRA DE SANTANA, BAHIA, BRASIL | M29: RUA AEROLINHA ESPANHA | N29: 80 | O29: GEORGE AMERICO | P29: FEIRA DE SANTANA | Q29: RUA AEROLINHA ESPANHA, N° 80, PROX: POLICLINICA DE GEORGE AMERICO | R29: PROX: POLICLINICA DE GEORGE AMERICO
A30: SIM | C30: =_xlfn.XLOOKUP(H30,RH!$D$2:$D$116,RH!$C$2:$C$116,"Terceiro") -> 81218214 | D30: =E30&" - "&F30 -> 1T - ROTA/5 | E30: 1T | F30: ROTA/5 | G30: EDUARDO S. | H30: EDUARDO DE ALMEIDA SILVA | I30: PEPSICO | J30: =_xlfn.XLOOKUP(H30,RH!$D$2:$D$116,RH!$K$2:$K$116,"Terceiro") -> BR1A004 | K30: 45789 | L30: =M30 & ", " & N30 & ", " & O30 & ", " & P30 & ", BAHIA" & ", BRASIL" -> RUA SEIS, 7, FEIRA VII, FEIRA DE SANTANA, BAHIA, BRASIL | M30: RUA SEIS | N30: 7 | O30: FEIRA VII | P30: FEIRA DE SANTANA | Q30: RUA SEIS, N° 7 - COM.J ELZA AZEVEDO | R30: COM.J ELZA AZEVEDO
A31: SIM | C31: =_xlfn.XLOOKUP(H31,RH!$D$2:$D$116,RH!$C$2:$C$116,"Terceiro") -> 40185173 | D31: =E31&" - "&F31 -> 3T - ROTA/1 | E31: 3T | F31: ROTA/1 | G31: Edvan. B | H31: EDVAN SOUZA SANTA BARBARA | I31: PEPSICO | J31: =_xlfn.XLOOKUP(H31,RH!$D$2:$D$116,RH!$K$2:$K$116,"Terceiro") -> BR1A007 | K31: 40924 | L31: =M31 & ", " & N31 & ", " & O31 & ", " & P31 & ", BAHIA" & ", BRASIL" -> Rua Camboriú, 50, SIM, FEIRA DE SANTANA, BAHIA, BRASIL | M31: Rua Camboriú | N31: 50 | O31: SIM | P31: FEIRA DE SANTANA | Q31: Rua Camboriú,N° 50, Ponto de apanha em frente a concessionaria Chery | R31: Atras do Shopping Avenida
A32: SIM | C32: =_xlfn.XLOOKUP(H32,RH!$D$2:$D$116,RH!$C$2:$C$116,"Terceiro") -> 40175823 | D32: =E32&" - "&F32 -> 2T - ROTA/5 | E32: 2T | F32: ROTA/5 | G32: ELAINE. G | H32: ELAINE BATISTA GONCALVES LIMA | I32: PEPSICO | J32: =_xlfn.XLOOKUP(H32,RH!$D$2:$D$116,RH!$K$2:$K$116,"Terceiro") -> BR1A294 | K32: 40756 | L32: =M32 & ", " & N32 & ", " & O32 & ", " & P32 & ", BAHIA" & ", BRASIL" -> RUA PROFª. ELISA FERNANDES, 23, CAMPO LIMPO, FEIRA DE SANTANA, BAHIA, BRASIL | M32: RUA PROFª. ELISA FERNANDES | N32: 23 | O32: CAMPO LIMPO | P32: FEIRA DE SANTANA | Q32: RUA PROFª. ELISA FERNANDES,Nº 23, PONTO DE APANHA BARBEARIA JB | R32: BARBEARIA JB
A33: SIM | C33: =_xlfn.XLOOKUP(H33,RH!$D$2:$D$116,RH!$C$2:$C$116,"Terceiro") -> 80851941 | D33: =E33&" - "&F33 -> 1T - ROTA/5 | E33: 1T | F33: ROTA/5 | G33: ELIANA. A | H33: ELIANA DE ALMEIDA OLIVEIRA | I33: PEPSICO | J33: =_xlfn.XLOOKUP(H33,RH!$D$2:$D$116,RH!$K$2:$K$116,"Terceiro") -> BR1A010 | K33: 44382 | L33: =M33 & ", " & N33 & ", " & O33 & ", " & P33 & ", BAHIA" & ", BRASIL" -> RUA PROJETADA, 27, PANORAMA, FEIRA DE SANTANA, BAHIA, BRASIL | M33: RUA PROJETADA | N33: 27 | O33: PANORAMA | P33: FEIRA DE SANTANA | Q33: RUA PROJETADA, N° 27 - RUA LATERAL DO USF PANORAMA 3 | R33: RUA LATERAL DO USF PANORAMA 3
A34: SIM | C34: =_xlfn.XLOOKUP(H34,RH!$D$2:$D$116,RH!$C$2:$C$116,"Terceiro") -> 40285831 | D34: =E34&" - "&F34 -> 1T - ROTA/2 | E34: 1T | F34: ROTA/2 | G34: ELIAS. F | H34: ELIAS MOREIRA DA FONSECA | I34: PEPSICO | J34: =_xlfn.XLOOKUP(H34,RH!$D$2:$D$116,RH!$K$2:$K$116,"Terceiro") -> BR1A010 | K34: 41925 | L34: =M34 & ", " & N34 & ", " & O34 & ", " & P34 & ", BAHIA" & ", BRASIL" -> PRAÇA SÃO ROQUE, N/A, MATINHA, MATINHA, BAHIA, BRASIL | M34: PRAÇA SÃO ROQUE | N34: N/A | O34: MATINHA | P34: MATINHA | Q34: PRAÇA SÃO ROQUE | R34: PRAÇA SÃO ROQUE
A35: SIM | C35: =_xlfn.XLOOKUP(H35,RH!$D$2:$D$116,RH!$C$2:$C$116,"Terceiro") -> 80997938 | D35: =E35&" - "&F35 -> 1T - ROTA/5 | E35: 1T | F35: ROTA/5 | G35: ELICELIA. C | H35: ELICELIA CAMPOS SANTOS | I35: PEPSICO | J35: =_xlfn.XLOOKUP(H35,RH!$D$2:$D$116,RH!$K$2:$K$116,"Terceiro") -> BR1A009 | K35: 44872 | L35: =M35 & ", " & N35 & ", " & O35 & ", " & P35 & ", BAHIA" & ", BRASIL" -> RESIDENCIAL MORADA FELIZ, RUA 1, N/A, FRATERNIDADE, FEIRA DE SANTANA, BAHIA, BRASIL | M35: RESIDENCIAL MORADA FELIZ, RUA 1 | N35: N/A | O35: FRATERNIDADE | P35: FEIRA DE SANTANA | Q35: RESIDENCIAL MORADA FELIZ, RUA 1, PONTO DE APANHA EM FRENTE A FABRICA VIVA NATUREZA | R35: EM FRENTE A FABRICA VIVA NATUREZA
A36: SIM | C36: =_xlfn.XLOOKUP(H36,RH!$D$2:$D$116,RH!$C$2:$C$116,"Terceiro") -> Terceiro | D36: =E36&" - "&F36 -> ADM ESPECIAL - ROTA/5 | E36: ADM ESPECIAL | F36: ROTA/5 | G36: ELINE P. | H36: ELINE PEREIRA ALVES | I36: LIMGER | J36: BR4A006 | K36: 45665 | L36: =M36 & ", " & N36 & ", " & O36 & ", " & P36 & ", BAHIA" & ", BRASIL" -> RUA AEROLINA ESPANHA, N/A, GEORGE AMERICO, FEIRA DE SANTANA, BAHIA, BRASIL | M36: RUA AEROLINA ESPANHA | N36: N/A | O36: GEORGE AMERICO | P36: FEIRA DE SANTANA | Q36: IGREJA ARCA DA ALIANÇA, EM FRENTE AO MERCADINHO DE DETE | R36: IGREJA ARCA DA ALIANÇA, EM FRENTE AO MERCADINHO DE DETE
A37: SIM | C37: =_xlfn.XLOOKUP(H37,RH!$D$2:$D$116,RH!$C$2:$C$116,"Terceiro") -> 40277251 | D37: =E37&" - "&F37 -> 1T - ROTA/4 | E37: 1T | F37: ROTA/4 | G37: ELIOMAR. P | H37: ELIOMAR CARVALHO DA PAIXAO | I37: PEPSICO | J37: =_xlfn.XLOOKUP(H37,RH!$D$2:$D$116,RH!$K$2:$K$116,"Terceiro") -> BR1A010 | K37: 41792 | L37: =M37 & ", " & N37 & ", " & O37 & ", " & P37 & ", BAHIA" & ", BRASIL" -> AV. RUBENS DE CARVALHO, 265, VILA OLIMPIA, FEIRA DE SANTANA, BAHIA, BRASIL | M37: AV. RUBENS DE CARVALHO | N37: 265 | O37: VILA OLIMPIA | P37: FEIRA DE SANTANA | Q37: AV. RUBENS DE CARVALHO, N° 265, EM FRENTE AO COND. SÃO BENTO | R37: EM FRENTE AO COND. SÃO BENTO
A38: SIM | C38: =_xlfn.XLOOKUP(H38,RH!$D$2:$D$116,RH!$C$2:$C$116,"Terceiro") -> 40297022 | D38: =E38&" - "&F38 -> 1T - ROTA/8 | E38: 1T | F38: ROTA/8 | G38: EMANUEL A. | H38: EMANUEL ALMEIDA DE LIMA | I38: PEPSICO | J38: =_xlfn.XLOOKUP(H38,RH!$D$2:$D$116,RH!$K$2:$K$116,"Terceiro") -> BR1A312 | K38: 42142 | L38: =M38 & ", " & N38 & ", " & O38 & ", " & P38 & ", BAHIA" & ", BRASIL" -> RUA ALTO DE SANTANA, N/A, GABRIELA, FEIRA DE SANTANA, BAHIA, BRASIL | M38: RUA ALTO DE SANTANA | N38: N/A | O38: GABRIELA | P38: FEIRA DE SANTANA | Q38: RUA ALTO DE SANTANA EM FRENTE AO MERCADO 3 IRMÃO | R38: EM FRENTE AO MERCADO 3 IRMÃO
A39: SIM | C39: =_xlfn.XLOOKUP(H39,RH!$D$2:$D$116,RH!$C$2:$C$116,"Terceiro") -> 80185857 | D39: =E39&" - "&F39 -> 2T - ROTA/2 | E39: 2T | F39: ROTA/2 | G39: EMANUELLA S. | H39: EMANUELA BATISTA SANTOS | I39: PEPSICO | J39: =_xlfn.XLOOKUP(H39,RH!$D$2:$D$116,RH!$K$2:$K$116,"Terceiro") -> BR1A312 | K39: 43598 | L39: =M39 & ", " & N39 & ", " & O39 & ", " & P39 & ", BAHIA" & ", BRASIL" -> RUA QUINTANDUBA, 103, CONCEIÇÃO I, FEIRA DE SANTANA, BAHIA, BRASIL | M39: RUA QUINTANDUBA | N39: 103 | O39: CONCEIÇÃO I | P39: FEIRA DE SANTANA | Q39: RUA QUINTANDUBA 103 EM FRENTE AO MERCADINHO FAMILIA SOUZA | R39: MERCADINHO FAMILIA SOUZA
A40: SIM | C40: =_xlfn.XLOOKUP(H40,RH!$D$2:$D$116,RH!$C$2:$C$116,"Terceiro") -> 80143927 | D40: =E40&" - "&F40 -> 2T - ROTA/5 | E40: 2T | F40: ROTA/5 | G40: ESMERALDA. M | H40: ESMERALDA MARTINS DO NASCIMENTO MAGALHAES | I40: PEPSICO | J40: =_xlfn.XLOOKUP(H40,RH!$D$2:$D$116,RH!$K$2:$K$116,"Terceiro") -> BR1A312 | K40: 43353 | L40: =M40 & ", " & N40 & ", " & O40 & ", " & P40 & ", BAHIA" & ", BRASIL" -> RUA J, 26, CIDADE NOVA, FEIRA DE SANTANA, BAHIA, BRASIL | M40: RUA J | N40: 26 | O40: CIDADE NOVA | P40: FEIRA DE SANTANA | Q40: RUA J, N° 26,PONTO DE APANHA BARATA MOTO PEÇAS | R40: BARATA MOTO PEÇAS
A41: SIM | C41: =_xlfn.XLOOKUP(H41,RH!$D$2:$D$116,RH!$C$2:$C$116,"Terceiro") -> 80013790 | D41: =E41&" - "&F41 -> 2T - ROTA/4 | E41: 2T | F41: ROTA/4 | G41: FERNANDO. M | H41: FERNANDO DA SILVA MOREIRA | I41: PEPSICO | J41: =_xlfn.XLOOKUP(H41,RH!$D$2:$D$116,RH!$K$2:$K$116,"Terceiro") -> BR1A312 | K41: 42436 | L41: =M41 & ", " & N41 & ", " & O41 & ", " & P41 & ", BAHIA" & ", BRASIL" -> RUA ESPAÇO SIDERAL, 15, AMELIA RODRIGUES, FEIRA DE SANTANA, BAHIA, BRASIL | M41: RUA ESPAÇO SIDERAL | N41: 15 | O41: AMELIA RODRIGUES | P41: FEIRA DE SANTANA | Q41: RUA ESPAÇO SIDERAL, Nº 15 | R41: A CASA DA FAZENDA
A42: SIM | C42: =_xlfn.XLOOKUP(H42,RH!$D$2:$D$116,RH!$C$2:$C$116,"Terceiro") -> 81003485 | D42: =E42&" - "&F42 -> 3T - ROTA/1 | E42: 3T | F42: ROTA/1 | G42: Fernando. G | H42: FERNANDO GONCALVES ALVES | I42: PEPSICO | J42: =_xlfn.XLOOKUP(H42,RH!$D$2:$D$116,RH!$K$2:$K$116,"Terceiro") -> BR1A312 | K42: 44900 | L42: =M42 & ", " & N42 & ", " & O42 & ", " & P42 & ", BAHIA" & ", BRASIL" -> CENTRO ESTADUAL DE EDUCAÇÃO PROFISSIONAL ÁUREO DE OLIVEIRA FILHO, N/A, SANTA MÔNICA, FEIRA DE SANTANA, BAHIA, BRASIL | M42: CENTRO ESTADUAL DE EDUCAÇÃO PROFISSIONAL ÁUREO DE OLIVEIRA FILHO | N42: N/A | O42: SANTA MÔNICA | P42: FEIRA DE SANTANA | Q42: Em frente ao Centro Estadual de Educação Profissional Aureo de Oliveira Filho | R42: Em frente ao Centro Estadual de Educação Profissional Aureo de Oliveira Filho
A43: SIM | C43: =_xlfn.XLOOKUP(H43,RH!$D$2:$D$116,RH!$C$2:$C$116,"Terceiro") -> 81033775 | D43: =E43&" - "&F43 -> 3T - ROTA/1 | E43: 3T | F43: ROTA/1 | G43: Forlan R. | H43: FORLAN RIBEIRO CARDOSO | I43: PEPSICO | J43: =_xlfn.XLOOKUP(H43,RH!$D$2:$D$116,RH!$K$2:$K$116,"Terceiro") -> BR1A312 | K43: 45019 | L43: =M43 & ", " & N43 & ", " & O43 & ", " & P43 & ", BAHIA" & ", BRASIL" -> Rua Irece, 35, JARDIM CRUZEIRO, FEIRA DE SANTANA, BAHIA, BRASIL | M43: Rua Irece | N43: 35 | O43: JARDIM CRUZEIRO | P43: FEIRA DE SANTANA | Q43: Rua Irece, N° 35 | R43: Drogaria Brito
A44: SIM | C44: =_xlfn.XLOOKUP(H44,RH!$D$2:$D$116,RH!$C$2:$C$116,"Terceiro") -> 80852123 | D44: =E44&" - "&F44 -> 2T - ROTA/3 | E44: 2T | F44: ROTA/3 | G44: FRANCISCA. L | H44: FRANCISCA ERLIANE DE LIMA | I44: PEPSICO | J44: =_xlfn.XLOOKUP(H44,RH!$D$2:$D$116,RH!$K$2:$K$116,"Terceiro") -> BR2A032 | K44: 44382 | L44: =M44 & ", " & N44 & ", " & O44 & ", " & P44 & ", BAHIA" & ", BRASIL" -> RUA SÃO CRISTOVÃO, 351, SANTA MÔNICA, FEIRA DE SANTANA, BAHIA, BRASIL | M44: RUA SÃO CRISTOVÃO | N44: 351 | O44: SANTA MÔNICA | P44: FEIRA DE SANTANA | Q44: RUA SÃO CRISTOVÃO, 351 - REF. PRÉDIO AZUL MARINHO | R44: PRÉDIO AZUL MARINHO
A45: SIM | C45: =_xlfn.XLOOKUP(H45,RH!$D$2:$D$116,RH!$C$2:$C$116,"Terceiro") -> 81170000 | D45: =E45&" - "&F45 -> 1T - ROTA/10 | E45: 1T | F45: ROTA/10 | G45: FRANCISCO A. | H45: FRANCISCO DE ASSIS SILVA MAGALHAES | I45: PEPSICO | J45: =_xlfn.XLOOKUP(H45,RH!$D$2:$D$116,RH!$K$2:$K$116,"Terceiro") -> BR1A312 | K45: 45516 | L45: =M45 & ", " & N45 & ", " & O45 & ", " & P45 & ", BAHIA" & ", BRASIL" -> RUA DA AVIAÇÃO, 565, CAMPO LIMPO, FEIRA DE SANTANA, BAHIA, BRASIL | M45: RUA DA AVIAÇÃO | N45: 565 | O45: CAMPO LIMPO | P45: FEIRA DE SANTANA | Q45: RUA DA AVIAÇÃO, Nº 565 | R45: RUA DA AVIAÇÃO, Nº 565
A46: SIM | C46: =_xlfn.XLOOKUP(H46,RH!$D$2:$D$116,RH!$C$2:$C$116,"Terceiro") -> Terceiro | D46: =E46&" - "&F46 -> 2T - ROTA/2 | E46: 2T | F46: ROTA/2 | G46: GABRIEL O. | H46: GABRIEL OLIVEIRA DE CARVALHO | I46: LIMGER | J46: BR4A006 | K46: 45665 | L46: =M46 & ", " & N46 & ", " & O46 & ", " & P46 & ", BAHIA" & ", BRASIL" -> AV. IGUATEMI, 528, , FEIRA DE SANTANA, BAHIA, BRASIL | M46: AV. IGUATEMI | N46: 528 | P46: FEIRA DE SANTANA | Q46: AV. IGUATEMI, 528, PROX. AO MERCADINHO CARIOCA | R46: MERCADINHO CARIOCA
A47: SIM | C47: =_xlfn.XLOOKUP(H47,RH!$D$2:$D$116,RH!$C$2:$C$116,"Terceiro") -> 81232514 | D47: =E47&" - "&F47 -> 2T - ROTA/2 | E47: 2T | F47: ROTA/2 | G47: GABRIELLE CASAES SANTANA | H47: GABRIELLE CASAES SANTANA | I47: PEPSICO | J47: =_xlfn.XLOOKUP(H47,RH!$D$2:$D$116,RH!$K$2:$K$116,"Terceiro") -> BR1A002 | L47: =M47 & ", " & N47 & ", " & O47 & ", " & P47 & ", BAHIA" & ", BRASIL" -> RUA DESEMBARGADOR RAYMUNDO CARNEIRO PINTO, 66, SIM, FEIRA DE SANTANA, BAHIA, BRASIL | M47: RUA DESEMBARGADOR RAYMUNDO CARNEIRO PINTO | N47: 66 | O47: SIM | P47: FEIRA DE SANTANA | Q47: RUA DESEMBARGADOR RAYMUNDO CARNEIRO PINTO, Nº 66
A48: SIM | C48: =_xlfn.XLOOKUP(H48,RH!$D$2:$D$116,RH!$C$2:$C$116,"Terceiro") -> 81193221 | D48: =E48&" - "&F48 -> 3T - ROTA/1 | E48: 3T | F48: ROTA/1 | G48: Gean Fonseca | H48: GEAN CLEBERSON MOTA DA FONSECA | I48: PEPSICO | J48: =_xlfn.XLOOKUP(H48,RH!$D$2:$D$116,RH!$K$2:$K$116,"Terceiro") -> BR1A004 | K48: 45663 | L48: =M48 & ", " & N48 & ", " & O48 & ", " & P48 & ", BAHIA" & ", BRASIL" -> Rua Corunha, 296, CONCEIÇÃO I, FEIRA DE SANTANA, BAHIA, BRASIL | M48: Rua Corunha | N48: 296 | O48: CONCEIÇÃO I | P48: FEIRA DE SANTANA | Q48: Rua Corunha, N° 296
A49: SIM | C49: =_xlfn.XLOOKUP(H49,RH!$D$2:$D$116,RH!$C$2:$C$116,"Terceiro") -> Terceiro | D49: =E49&" - "&F49 -> 1T - ROTA/5 | E49: 1T | F49: ROTA/5 | G49: GILSON DOS S. | H49: GILSON DOS SANTOS SILVA | I49: LIMGER | J49: BR4A006 | K49: 45665 | L49: =M49 & ", " & N49 & ", " & O49 & ", " & P49 & ", BAHIA" & ", BRASIL" -> RUA EL SALVADOR, 2543, FEIRA VII, FEIRA DE SANTANA, BAHIA, BRASIL | M49: RUA EL SALVADOR | N49: 2543 | O49: FEIRA VII | P49: FEIRA DE SANTANA | Q49: RUA EL SALVador, N° 2543 - SUPERMERCADO LIMA | R49: SUPERMERCADO LIMA
A50: SIM | C50: =_xlfn.XLOOKUP(H50,RH!$D$2:$D$116,RH!$C$2:$C$116,"Terceiro") -> 80900231 | D50: =E50&" - "&F50 -> ADM - ROTA/2 | E50: ADM | F50: ROTA/2 | G50: IASMIM L. | H50: IASMIM DE ALMEIDA LIMA | I50: PEPSICO | J50: =_xlfn.XLOOKUP(H50,RH!$D$2:$D$116,RH!$K$2:$K$116,"Terceiro") -> BR1A002 | K50: 44564 | L50: =M50 & ", " & N50 & ", " & O50 & ", " & P50 & ", BAHIA" & ", BRASIL" -> RUA ALMEIDA DAS ARVORES, N/A, MANGABEIRA, FEIRA DE SANTANA, BAHIA, BRASIL | M50: RUA ALMEIDA DAS ARVORES | N50: N/A | O50: MANGABEIRA | P50: FEIRA DE SANTANA | Q50: RUA ALMEIDA DAS ARVORES | R50: EM FRENTE AO MERCADINHO ARMAZÉM
A51: SIM | C51: =_xlfn.XLOOKUP(H51,RH!$D$2:$D$116,RH!$C$2:$C$116,"Terceiro") -> Terceiro | D51: =E51&" - "&F51 -> 2T - ROTA/3 | E51: 2T | F51: ROTA/3 | G51: IRACI MARIA DE J. | H51: IRACI MARIA DE JESUS | I51: LIMGER | J51: BR4A006 | K51: 45665 | L51: =M51 & ", " & N51 & ", " & O51 & ", " & P51 & ", BAHIA" & ", BRASIL" -> RUA MOGI DAS CRUZES, N/A, , FEIRA DE SANTANA, BAHIA, BRASIL | M51: RUA MOGI DAS CRUZES | N51: N/A | P51: FEIRA DE SANTANA | Q51: RUA MOGI DAS CRUZES, AO LADO DO COLÉGIO JUIZ JORGE FARIAS GOES | R51: AO LADO DO COLÉGIO JUIZ JORGE FARIAS GOES
A52: SIM | C52: =_xlfn.XLOOKUP(H52,RH!$D$2:$D$116,RH!$C$2:$C$116,"Terceiro") -> Terceiro | D52: =E52&" - "&F52 -> ADM ESPECIAL - ROTA/2 | E52: ADM ESPECIAL | F52: ROTA/2 | G52: ISAIAS DE JESUS | H52: ISAIAS DE JESUS | I52: LIMGER | J52: BR4A006 | K52: 45665 | L52: =M52 & ", " & N52 & ", " & O52 & ", " & P52 & ", BAHIA" & ", BRASIL" -> RUA QUINTO, 1027, SANTO ANTÔNIO DOS PRAZERES, FEIRA DE SANTANA, BAHIA, BRASIL | M52: RUA QUINTO | N52: 1027 | O52: SANTO ANTÔNIO DOS PRAZERES | P52: FEIRA DE SANTANA | Q52: RUA QUINTO | R52: FUNDO DO POSTO DE GASOLINA JG
A53: SIM | C53: =_xlfn.XLOOKUP(H53,RH!$D$2:$D$116,RH!$C$2:$C$116,"Terceiro") -> 40192597 | D53: =E53&" - "&F53 -> ADM - ROTA/5 | E53: ADM | F53: ROTA/5 | G53: ISMAEL. P | H53: ISMAEL PORTUGAL DE ALMEIDA | I53: PEPSICO | J53: =_xlfn.XLOOKUP(H53,RH!$D$2:$D$116,RH!$K$2:$K$116,"Terceiro") -> BR1A008 | K53: 41102 | L53: =M53 & ", " & N53 & ", " & O53 & ", " & P53 & ", BAHIA" & ", BRASIL" -> RUA TERESOPOLIS II, 29, CAMPO LIMPO, FEIRA DE SANTANA, BAHIA, BRASIL | M53: RUA TERESOPOLIS II | N53: 29 | O53: CAMPO LIMPO | P53: FEIRA DE SANTANA | Q53: FUNDO DO SENAI | R53: FUNDO DO SENAI
A54: SIM | C54: =_xlfn.XLOOKUP(H54,RH!$D$2:$D$116,RH!$C$2:$C$116,"Terceiro") -> Terceiro | D54: =E54&" - "&F54 -> ADM - ROTA/1 | E54: ADM | F54: ROTA/1 | G54: ITALO S. | H54: ITALO ANDRADE SOUSA | I54: MANPOWER | J54: BR4A004 | K54: 45147 | L54: =M54 & ", " & N54 & ", " & O54 & ", " & P54 & ", BAHIA" & ", BRASIL" -> Avenida Artêmia Pires, 8147, Sim, FEIRA DE SANTANA, BAHIA, BRASIL | M54: Avenida Artêmia Pires | N54: 8147 | O54: Sim | P54: FEIRA DE SANTANA | Q54: COND. PARQUE FLORA | R54: COND. PARQUE FLORA
A55: SIM | C55: =_xlfn.XLOOKUP(H55,RH!$D$2:$D$116,RH!$C$2:$C$116,"Terceiro") -> 40221612 | D55: =E55&" - "&F55 -> 2T - ROTA/4 | E55: 2T | F55: ROTA/4 | G55: IVANILDO. F | H55: IVANILDO FERREIRA DOS SANTOS NASCIMENTO | I55: PEPSICO | J55: =_xlfn.XLOOKUP(H55,RH!$D$2:$D$116,RH!$K$2:$K$116,"Terceiro") -> BR1A004 | K55: 41561 | L55: =M55 & ", " & N55 & ", " & O55 & ", " & P55 & ", BAHIA" & ", BRASIL" -> RUA GENÉSIO MOREIRA, 283, HUMILDES, HUMILDES, BAHIA, BRASIL | M55: RUA GENÉSIO MOREIRA | N55: 283 | O55: HUMILDES | P55: HUMILDES | Q55: RUA GENÉSIO MOREIRA N°283 | R55: A IGREJA NOVA DE CRISTO
A56: SIM | C56: =_xlfn.XLOOKUP(H56,RH!$D$2:$D$116,RH!$C$2:$C$116,"Terceiro") -> 81050387 | D56: =E56&" - "&F56 -> 1T - ROTA/6 | E56: 1T | F56: ROTA/6 | G56: JADNA A. | H56: JADNA ALMEIDA ESTRELA | I56: PEPSICO | J56: =_xlfn.XLOOKUP(H56,RH!$D$2:$D$116,RH!$K$2:$K$116,"Terceiro") -> BR1A002 | K56: 45082 | L56: =M56 & ", " & N56 & ", " & O56 & ", " & P56 & ", BAHIA" & ", BRASIL" -> RUA DO ROSARIO, 100, MANGABEIRA, FEIRA DE SANTANA, BAHIA, BRASIL | M56: RUA DO ROSARIO | N56: 100 | O56: MANGABEIRA | P56: FEIRA DE SANTANA | Q56: RUA DO ROSARIO, Nº 100, EM FRENTE AO CONDOMINIO IDEALE GIARDINI, REF:AÇOUGUE REI DO GADO | R56: AÇOUGUE REI DO GADO
A57: SIM | C57: =_xlfn.XLOOKUP(H57,RH!$D$2:$D$116,RH!$C$2:$C$116,"Terceiro") -> 80872720 | D57: =E57&" - "&F57 -> 3T - ROTA/2 | E57: 3T | F57: ROTA/2 | G57: Jadson. S | H57: JADSON DE JESUS SANTANA | I57: PEPSICO | J57: =_xlfn.XLOOKUP(H57,RH!$D$2:$D$116,RH!$K$2:$K$116,"Terceiro") -> BR1A004 | K57: 44459 | L57: =M57 & ", " & N57 & ", " & O57 & ", " & P57 & ", BAHIA" & ", BRASIL" -> Rua Isaias Gonçalves, 227, TOMBA, FEIRA DE SANTANA, BAHIA, BRASIL | M57: Rua Isaias Gonçalves | N57: 227 | O57: TOMBA | P57: FEIRA DE SANTANA | Q57: Rua Isaias Gonçalves, N° 227 | R57: Prox: A Paróquia
A58: SIM | C58: =_xlfn.XLOOKUP(H58,RH!$D$2:$D$116,RH!$C$2:$C$116,"Terceiro") -> 40192681 | D58: =E58&" - "&F58 -> 2T - ROTA/1 | E58: 2T | F58: ROTA/1 | G58: JEANDERSON. N | H58: JEANDERSON BATISTA NASCIMENTO | I58: PEPSICO | J58: =_xlfn.XLOOKUP(H58,RH!$D$2:$D$116,RH!$K$2:$K$116,"Terceiro") -> BR1A312 | K58: 41107 | L58: =M58 & ", " & N58 & ", " & O58 & ", " & P58 & ", BAHIA" & ", BRASIL" -> RUA AMADO BAHIA, N/A, PANORAMA, FEIRA DE SANTANA, BAHIA, BRASIL | M58: RUA AMADO BAHIA | N58: N/A | O58: PANORAMA | P58: FEIRA DE SANTANA | Q58: RUA AMADO BAHIA EM FRENTE A IGREJA DAS TESTEMUNHAS DE JEOVÁ | R58: IGREJA DAS TESTEMUNHAS DE JEOVÁ
A59: SIM | C59: =_xlfn.XLOOKUP(H59,RH!$D$2:$D$116,RH!$C$2:$C$116,"Terceiro") -> 80007458 | D59: =E59&" - "&F59 -> 1T - ROTA/6 | E59: 1T | F59: ROTA/6 | G59: JEFERSON A. | H59: JEFERSON DO AMARAL SANTOS | I59: PEPSICO | J59: =_xlfn.XLOOKUP(H59,RH!$D$2:$D$116,RH!$K$2:$K$116,"Terceiro") -> BR1A312 | K59: 42268 | L59: =M59 & ", " & N59 & ", " & O59 & ", " & P59 & ", BAHIA" & ", BRASIL" -> AV. ANTONIO RIBEIRO MARQUES, N/A, SIM, FEIRA DE SANTANA, BAHIA, BRASIL | M59: AV. ANTONIO RIBEIRO MARQUES | N59: N/A | O59: SIM | P59: FEIRA DE SANTANA | Q59: AV. ANTONIO RIBEIRO MARQUES, PONTO DE APANHA EM FRENTE AO COND: RESERVA IBIRAPUERA | R59: EM FRENTE AO COND: RESERVA IBIRAPUERA
A60: SIM | C60: =_xlfn.XLOOKUP(H60,RH!$D$2:$D$116,RH!$C$2:$C$116,"Terceiro") -> 40296986 | D60: =E60&" - "&F60 -> 1T - ROTA/4 | E60: 1T | F60: ROTA/4 | G60: JENIVALDO. S | H60: JENIVALDO DE JESUS DA SILVA | I60: PEPSICO | J60: =_xlfn.XLOOKUP(H60,RH!$D$2:$D$116,RH!$K$2:$K$116,"Terceiro") -> BR1A312 | K60: 42142 | L60: =M60 & ", " & N60 & ", " & O60 & ", " & P60 & ", BAHIA" & ", BRASIL" -> RUA B, CAMINHO E16, 11, FEIRA X, FEIRA DE SANTANA, BAHIA, BRASIL | M60: RUA B, CAMINHO E16 | N60: 11 | O60: FEIRA X | P60: FEIRA DE SANTANA | Q60: RUA B, CAMINHO E16, N° 11 | R60: RUA B, CAMINHO E16, N° 11
A61: SIM | C61: =_xlfn.XLOOKUP(H61,RH!$D$2:$D$116,RH!$C$2:$C$116,"Terceiro") -> 81251042 | D61: =E61&" - "&F61 -> 1T - ROTA/6 | E61: 1T | F61: ROTA/6 | G61: JOACI S. | H61: JOACI SANTOS DA SILVA | I61: PEPSICO | J61: =_xlfn.XLOOKUP(H61,RH!$D$2:$D$116,RH!$K$2:$K$116,"Terceiro") -> BR1A004 | K61: 46027 | L61: =M61 & ", " & N61 & ", " & O61 & ", " & P61 & ", BAHIA" & ", BRASIL" -> RUA CATOLÉ DA ROCHA, 930, SANTO ANTÔNIO DOS PRAZERES, FEIRA DE SANTANA, BAHIA, BRASIL | M61: RUA CATOLÉ DA ROCHA | N61: 930 | O61: SANTO ANTÔNIO DOS PRAZERES | P61: FEIRA DE SANTANA | Q61: POSTO DE COMBUSTIVEL SANTA FÉ
A62: SIM | C62: =_xlfn.XLOOKUP(H62,RH!$D$2:$D$116,RH!$C$2:$C$116,"Terceiro") -> Terceiro | D62: =E62&" - "&F62 -> ADM - ROTA/7 | E62: ADM | F62: ROTA/7 | G62: JOÃO ROBERTO DE S. | H62: JOÃO ROBERTO DE SENA GOMES | I62: LIMGER | J62: BR4A006 | K62: 45665 | L62: =M62 & ", " & N62 & ", " & O62 & ", " & P62 & ", BAHIA" & ", BRASIL" -> Rua do Mercado, N/A, HUMILDES, HUMILDES, BAHIA, BRASIL | M62: Rua do Mercado | N62: N/A | O62: HUMILDES | P62: HUMILDES | Q62: EM FRENTE AO MERCADO MUNICIPAL | R62: MERCADO MUNICIPAL
A63: SIM | C63: =_xlfn.XLOOKUP(H63,RH!$D$2:$D$116,RH!$C$2:$C$116,"Terceiro") -> Terceiro | D63: =E63&" - "&F63 -> ADM ESPECIAL - ROTA/2 | E63: ADM ESPECIAL | F63: ROTA/2 | G63: JORGE MANOEL | H63: JORGE MANOEL DOS SANTOS | I63: LIMGER | J63: BR4A006 | K63: 45665 | L63: =M63 & ", " & N63 & ", " & O63 & ", " & P63 & ", BAHIA" & ", BRASIL" -> RUA RIO VERDE, 40, CONCEIÇÃO II, FEIRA DE SANTANA, BAHIA, BRASIL | M63: RUA RIO VERDE | N63: 40 | O63: CONCEIÇÃO II | P63: FEIRA DE SANTANA | Q63: RUA RIO VERDE | R63: NOVA PRAÇA CONCEIÇÃO II
A64: SIM | C64: =_xlfn.XLOOKUP(H64,RH!$D$2:$D$116,RH!$C$2:$C$116,"Terceiro") -> Terceiro | D64: =E64&" - "&F64 -> ADM - ROTA/3 | E64: ADM | F64: ROTA/3 | G64: JOSE DE JESUS A. | H64: JOSE DE JESUS ALMEIDA FILHO | I64: LIMGER | J64: BR4A006 | K64: 45665 | L64: =M64 & ", " & N64 & ", " & O64 & ", " & P64 & ", BAHIA" & ", BRASIL" -> RUA E, 81, AVIARIO, FEIRA DE SANTANA, BAHIA, BRASIL | M64: RUA E | N64: 81 | O64: AVIARIO | P64: FEIRA DE SANTANA | Q64: RUA E | R64: MERCADINHO AV
A65: SIM | C65: =_xlfn.XLOOKUP(H65,RH!$D$2:$D$116,RH!$C$2:$C$116,"Terceiro") -> 80981334 | D65: =E65&" - "&F65 -> 1T - ROTA/6 | E65: 1T | F65: ROTA/6 | G65: JOSE P. | H65: JOSE PHILIPE DE JESUS PINTO | I65: PEPSICO | J65: =_xlfn.XLOOKUP(H65,RH!$D$2:$D$116,RH!$K$2:$K$116,"Terceiro") -> BR1A294 | K65: 44823 | L65: =M65 & ", " & N65 & ", " & O65 & ", " & P65 & ", BAHIA" & ", BRASIL" -> RUA VITORINO FREIRE, 426, MANGABEIRA, FEIRA DE SANTANA, BAHIA, BRASIL | M65: RUA VITORINO FREIRE | N65: 426 | O65: MANGABEIRA | P65: FEIRA DE SANTANA | Q65: RUA VITORINO FREIRE, Nº 426 | R65: RUA VITORINO FREIRE, Nº 426
A66: SIM | C66: =_xlfn.XLOOKUP(H66,RH!$D$2:$D$116,RH!$C$2:$C$116,"Terceiro") -> 80157142 | D66: =E66&" - "&F66 -> 1T - ROTA/10 | E66: 1T | F66: ROTA/10 | G66: JOSEANE. B | H66: JOSEANE BASTOS DOS SANTOS | I66: PEPSICO | J66: =_xlfn.XLOOKUP(H66,RH!$D$2:$D$116,RH!$K$2:$K$116,"Terceiro") -> BR2A008 | K66: 43437 | L66: =M66 & ", " & N66 & ", " & O66 & ", " & P66 & ", BAHIA" & ", BRASIL" -> RUA C, 345, CAMPO LIMPO, FEIRA DE SANTANA, BAHIA, BRASIL | M66: RUA C | N66: 345 | O66: CAMPO LIMPO | P66: FEIRA DE SANTANA | Q66: RUA C, Nº 345 PROX: AO MERCADO BIG ECONOMICO OU MERCADO FILÉ | R66: PROX: AO MERCADO BIG ECONOMICO OU MERCADO FILÉ
A67: SIM | C67: =_xlfn.XLOOKUP(H67,RH!$D$2:$D$116,RH!$C$2:$C$116,"Terceiro") -> 80014736 | D67: =E67&" - "&F67 -> 1T - ROTA/1 | E67: 1T | F67: ROTA/1 | G67: JOSEMIR. C | H67: JOSEMIR BORGES DE CARVALHO | I67: PEPSICO | J67: =_xlfn.XLOOKUP(H67,RH!$D$2:$D$116,RH!$K$2:$K$116,"Terceiro") -> BR1A294 | K67: 42464 | L67: =M67 & ", " & N67 & ", " & O67 & ", " & P67 & ", BAHIA" & ", BRASIL" -> RUA GENÉSIO MOREIRA, 283, HUMILDES, HUMILDES, BAHIA, BRASIL | M67: RUA GENÉSIO MOREIRA | N67: 283 | O67: HUMILDES | P67: HUMILDES | Q67: RUA GENÉSIO MOREIRA N° 283 - PROX. A IGREJA NOVA DE CRISTO | R67: PROX. A IGREJA NOVA DE CRISTO
A68: SIM | C68: =_xlfn.XLOOKUP(H68,RH!$D$2:$D$116,RH!$C$2:$C$116,"Terceiro") -> Terceiro | D68: =E68&" - "&F68 -> 1T - ROTA/8 | E68: 1T | F68: ROTA/8 | G68: JOSENICE S. | H68: JOSENICE SANTOS DA CRUZ | I68: LIMGER | J68: BR4A006 | K68: 45665 | L68: =M68 & ", " & N68 & ", " & O68 & ", " & P68 & ", BAHIA" & ", BRASIL" -> RUA PROFª MARIA DA GLORIA DE JESUS, 61, GABRIELA, FEIRA DE SANTANA, BAHIA, BRASIL | M68: RUA PROFª MARIA DA GLORIA DE JESUS | N68: 61 | O68: GABRIELA | P68: FEIRA DE SANTANA | Q68: RUA PROFª MARIA DA GLORIA DE JESUS, N° 61, REF: MERCADINHO DONA JO | R68: MERCADINHO DONA JO
A69: SIM | C69: =_xlfn.XLOOKUP(H69,RH!$D$2:$D$116,RH!$C$2:$C$116,"Terceiro") -> 81033488 | D69: =E69&" - "&F69 -> 1T - ROTA/8 | E69: 1T | F69: ROTA/8 | G69: JULIANA A. | H69: JULIANA ALVES CIRIACO DOS SANTOS | I69: PEPSICO | J69: =_xlfn.XLOOKUP(H69,RH!$D$2:$D$116,RH!$K$2:$K$116,"Terceiro") -> BR1A312 | K69: 45019 | L69: =M69 & ", " & N69 & ", " & O69 & ", " & P69 & ", BAHIA" & ", BRASIL" -> RUA GENÉSIO SERAFIM DE LIMA, 17, GABRIELA, FEIRA DE SANTANA, BAHIA, BRASIL | M69: RUA GENÉSIO SERAFIM DE LIMA | N69: 17 | O69: GABRIELA | P69: FEIRA DE SANTANA | Q69: RUA GENÉSIO SERAFIM DE LIMA, N° 17, REF: DEPOSITO DE BEBIDAS JUNIOR CROSS | R69: DEPOSITO DE BEBIDAS JUNIOR CROSS
A70: SIM | C70: =_xlfn.XLOOKUP(H70,RH!$D$2:$D$116,RH!$C$2:$C$116,"Terceiro") -> 80304771 | D70: =E70&" - "&F70 -> ADM - ROTA/1 | E70: ADM | F70: ROTA/1 | G70: KATARYNA A. | H70: KATARYNNA SANTOS DE ARAUJO | I70: PEPSICO | J70: =_xlfn.XLOOKUP(H70,RH!$D$2:$D$116,RH!$K$2:$K$116,"Terceiro") -> BR1A054 | K70: 44179 | L70: =M70 & ", " & N70 & ", " & O70 & ", " & P70 & ", BAHIA" & ", BRASIL" -> Avenida Antônio Ribeiro Marques, 1801, Registro, FEIRA DE SANTANA, BAHIA, BRASIL | M70: Avenida Antônio Ribeiro Marques | N70: 1801 | O70: Registro | P70: FEIRA DE SANTANA | Q70: COND. RESERVA BUZIOS | R70: COND. RESERVA BUZIOS
A71: SIM | C71: =_xlfn.XLOOKUP(H71,RH!$D$2:$D$116,RH!$C$2:$C$116,"Terceiro") -> 81004104 | D71: =E71&" - "&F71 -> 1T - ROTA/7 | E71: 1T | F71: ROTA/7 | G71: LAILSON. C | H71: LAILSON DO CARMO DE SAO JOSE | I71: PEPSICO | J71: =_xlfn.XLOOKUP(H71,RH!$D$2:$D$116,RH!$K$2:$K$116,"Terceiro") -> BR1A009 | K71: 44900 | L71: =M71 & ", " & N71 & ", " & O71 & ", " & P71 & ", BAHIA" & ", BRASIL" -> Avenida Domício Alves de Andrade, 39, AMELIA RODRIGUES, AMELIA RODRIGUES, BAHIA, BRASIL | M71: Avenida Domício Alves de Andrade | N71: 39 | O71: AMELIA RODRIGUES | P71: AMELIA RODRIGUES | Q71: Avenida Domício Alves de Andrade, 39. Referência depois da embasa | R71: Depois da embasa
A72: SIM | C72: =_xlfn.XLOOKUP(H72,RH!$D$2:$D$116,RH!$C$2:$C$116,"Terceiro") -> 81150129 | D72: =E72&" - "&F72 -> 1T - ROTA/6 | E72: 1T | F72: ROTA/6 | G72: LEANDRO. B | H72: LEANDRO BARBOSA SOUZA | I72: PEPSICO | J72: =_xlfn.XLOOKUP(H72,RH!$D$2:$D$116,RH!$K$2:$K$116,"Terceiro") -> BR1A312 | K72: 45446 | L72: =M72 & ", " & N72 & ", " & O72 & ", " & P72 & ", BAHIA" & ", BRASIL" -> RUA DO ROSARIO, 100, MANGABEIRA, FEIRA DE SANTANA, BAHIA, BRASIL | M72: RUA DO ROSARIO | N72: 100 | O72: MANGABEIRA | P72: FEIRA DE SANTANA | Q72: RUA DO ROSARIO, Nº 100, EM FRENTE AO CONDOMINIO IDEALE GIARDINI | R72: AÇOUGUE REI DO GADO
A73: SIM | C73: =_xlfn.XLOOKUP(H73,RH!$D$2:$D$116,RH!$C$2:$C$116,"Terceiro") -> 80931429 | D73: =E73&" - "&F73 -> 1T - ROTA/4 | E73: 1T | F73: ROTA/4 | G73: LEANDRO. S | H73: LEANDRO SANTOS DA SILVA | I73: PEPSICO | J73: =_xlfn.XLOOKUP(H73,RH!$D$2:$D$116,RH!$K$2:$K$116,"Terceiro") -> BR1A312 | K73: 44669 | L73: =M73 & ", " & N73 & ", " & O73 & ", " & P73 & ", BAHIA" & ", BRASIL" -> RUA DANTAS, 91, EUCALIPTO, FEIRA DE SANTANA, BAHIA, BRASIL | M73: RUA DANTAS | N73: 91 | O73: EUCALIPTO | P73: FEIRA DE SANTANA | Q73: RUA DANTAS, 91 - PROX.AO COWBOY DO ASFALTO | R73: PROX.AO COWBOY DO ASFALTO
A74: SIM | C74: =_xlfn.XLOOKUP(H74,RH!$D$2:$D$116,RH!$C$2:$C$116,"Terceiro") -> 80187110 | D74: =E74&" - "&F74 -> 1T - ROTA/4 | E74: 1T | F74: ROTA/4 | G74: LEILA. C | H74: LEILA MIRELLA SOUSA SANTOS COSTA | I74: PEPSICO | J74: =_xlfn.XLOOKUP(H74,RH!$D$2:$D$116,RH!$K$2:$K$116,"Terceiro") -> BR1A312 | K74: 43598 | L74: =M74 & ", " & N74 & ", " & O74 & ", " & P74 & ", BAHIA" & ", BRASIL" -> RUA PILAR DO SUL, 1124, BRASILIA, FEIRA DE SANTANA, BAHIA, BRASIL | M74: RUA PILAR DO SUL | N74: 1124 | O74: BRASILIA | P74: FEIRA DE SANTANA | Q74: RUA PILAR DO SUL, N° 1124 PONTO DE APANHA: RUA EM FRENTE A FEIRA TAXI | R74: RUA EM FRENTE A FEIRA TAXI
A75: SIM | C75: =_xlfn.XLOOKUP(H75,RH!$D$2:$D$116,RH!$C$2:$C$116,"Terceiro") -> 81223120 | D75: =E75&" - "&F75 -> 1T - ROTA/9 | E75: 1T | F75: ROTA/9 | G75: LEONARDO. S | H75: LEONARDO DA SILVA SANTOS | I75: PEPSICO | J75: =_xlfn.XLOOKUP(H75,RH!$D$2:$D$116,RH!$K$2:$K$116,"Terceiro") -> BR1A004 | K75: 45817 | L75: =M75 & ", " & N75 & ", " & O75 & ", " & P75 & ", BAHIA" & ", BRASIL" -> AV. CAZUMBA, N/A, SÃO GONÇALO DOS CAMPOS, SÃO GONÇALO DOS CAMPOS, BAHIA, BRASIL | M75: AV. CAZUMBA | N75: N/A | O75: SÃO GONÇALO DOS CAMPOS | P75: SÃO GONÇALO DOS CAMPOS | Q75: AV. CAZUMBA EM FRENTE A SERRALHERIA SANTO ANTONIO | R75: EM FRENTE A SERRALHERIA SANTO ANTONIO
A76: SIM | C76: =_xlfn.XLOOKUP(H76,RH!$D$2:$D$116,RH!$C$2:$C$116,"Terceiro") -> 40182248 | D76: =E76&" - "&F76 -> 2T - ROTA/1 | E76: 2T | F76: ROTA/1 | G76: LHAIS. A | H76: LHAIS SILVA DOS ANJOS | I76: PEPSICO | J76: =_xlfn.XLOOKUP(H76,RH!$D$2:$D$116,RH!$K$2:$K$116,"Terceiro") -> BR2A032 | K76: 40861 | L76: =M76 & ", " & N76 & ", " & O76 & ", " & P76 & ", BAHIA" & ", BRASIL" -> RUA AMADO BAHIA, N/A, PANORAMA, FEIRA DE SANTANA, BAHIA, BRASIL | M76: RUA AMADO BAHIA | N76: N/A | O76: PANORAMA | P76: FEIRA DE SANTANA | Q76: RUA AMADO BAHIA EM FRENTE A IGREJA DAS TESTEMUNHAS DE JEOVÁ | R76: IGREJA DAS TESTEMUNHAS DE JEOVÁ
A77: SIM | C77: =_xlfn.XLOOKUP(H77,RH!$D$2:$D$116,RH!$C$2:$C$116,"Terceiro") -> 81051051 | D77: =E77&" - "&F77 -> 1T - ROTA/3 | E77: 1T | F77: ROTA/3 | G77: LUAN. B | H77: LUAN BENICIO BANDEIRA PINTO | I77: PEPSICO | J77: =_xlfn.XLOOKUP(H77,RH!$D$2:$D$116,RH!$K$2:$K$116,"Terceiro") -> BR1A294 | K77: 45082 | L77: =M77 & ", " & N77 & ", " & O77 & ", " & P77 & ", BAHIA" & ", BRASIL" -> PRAÇA QUATRO, 1, CIDADE NOVA, FEIRA DE SANTANA, BAHIA, BRASIL | M77: PRAÇA QUATRO | N77: 1 | O77: CIDADE NOVA | P77: FEIRA DE SANTANA | Q77: PRAÇA QUATRO, N° 01, PROX: AO COLEGIO LUIZ VIANA | R77: PROX: AO COLEGIO LUIZ VIANA
A78: SIM | C78: =_xlfn.XLOOKUP(H78,RH!$D$2:$D$116,RH!$C$2:$C$116,"Terceiro") -> 40201957 | D78: =E78&" - "&F78 -> ADM - ROTA/6 | E78: ADM | F78: ROTA/6 | G78: LUCAS DE O. R. | H78: LUCAS DE OLIVEIRA RODRIGUES | I78: PEPSICO | J78: =_xlfn.XLOOKUP(H78,RH!$D$2:$D$116,RH!$K$2:$K$116,"Terceiro") -> BR1A013 | K78: 41166 | L78: =M78 & ", " & N78 & ", " & O78 & ", " & P78 & ", BAHIA" & ", BRASIL" -> RUA MATO GROSSO, 50, SÃO GONÇALO DOS CAMPOS, SÃO GONÇALO DOS CAMPOS, BAHIA, BRASIL | M78: RUA MATO GROSSO | N78: 50 | O78: SÃO GONÇALO DOS CAMPOS | P78: SÃO GONÇALO DOS CAMPOS | Q78: RUA MATO GROSSO Nº 50 | R78: PRIMEIRA DIREITA, APÓS A ASSEMBLEIA DA RUA DA ALEGRIA
A79: SIM | C79: =_xlfn.XLOOKUP(H79,RH!$D$2:$D$116,RH!$C$2:$C$116,"Terceiro") -> 80851526 | D79: =E79&" - "&F79 -> 2T - ROTA/2 | E79: 2T | F79: ROTA/2 | G79: LUCIANE. L | H79: LUCIANE LIMA | I79: PEPSICO | J79: =_xlfn.XLOOKUP(H79,RH!$D$2:$D$116,RH!$K$2:$K$116,"Terceiro") -> BR1A312 | K79: 44382 | L79: =M79 & ", " & N79 & ", " & O79 & ", " & P79 & ", BAHIA" & ", BRASIL" -> RUA VITORINO FREIRE, 822, JARDIM EUROPA, FEIRA DE SANTANA, BAHIA, BRASIL | M79: RUA VITORINO FREIRE | N79: 822 | O79: JARDIM EUROPA | P79: FEIRA DE SANTANA | Q79: RUA VITORINO FREIRE, Nº 822 EM FRENTE AO COND: BERGAMO | R79: EM FRENTE AO COND: BERGAMO
A80: SIM | C80: =_xlfn.XLOOKUP(H80,RH!$D$2:$D$116,RH!$C$2:$C$116,"Terceiro") -> 40182881 | D80: =E80&" - "&F80 -> 1T - ROTA/3 | E80: 1T | F80: ROTA/3 | G80: LUIS ROGERIO. S. S. | H80: LUIS ROGERIO SOARES SANTANA | I80: PEPSICO | J80: =_xlfn.XLOOKUP(H80,RH!$D$2:$D$116,RH!$K$2:$K$116,"Terceiro") -> BR1A012 | K80: 40861 | L80: =M80 & ", " & N80 & ", " & O80 & ", " & P80 & ", BAHIA" & ", BRASIL" -> EM FRENTE AO MOTEL SCALA, N/A, CASEB, FEIRA DE SANTANA, BAHIA, BRASIL | M80: EM FRENTE AO MOTEL SCALA | N80: N/A | O80: CASEB | P80: FEIRA DE SANTANA | Q80: EM FRENTE AO MOTEL SCALA | R80: EM FRENTE AO MOTEL SCALA
A81: SIM | C81: =_xlfn.XLOOKUP(H81,RH!$D$2:$D$116,RH!$C$2:$C$116,"Terceiro") -> 80873151 | D81: =E81&" - "&F81 -> 1T - ROTA/1 | E81: 1T | F81: ROTA/1 | G81: LUIZ E. | H81: LUIZ EDUARDO DE OLIVEIRA SANTOS | I81: PEPSICO | J81: =_xlfn.XLOOKUP(H81,RH!$D$2:$D$116,RH!$K$2:$K$116,"Terceiro") -> BR1A010 | K81: 44459 | L81: =M81 & ", " & N81 & ", " & O81 & ", " & P81 & ", BAHIA" & ", BRASIL" -> RUA PRINCIPAL DO LIMOEIRO, 15-A, LIMOEIRO, LIMOEIRO, BAHIA, BRASIL | M81: RUA PRINCIPAL DO LIMOEIRO | N81: 15-A | O81: LIMOEIRO | P81: LIMOEIRO | Q81: RUA PRINCIPAL DO LIMOEIRO 15-A PONTO DE APANHA : OFICINA LULA BIKE | R81: OFICINA LULA BIKE
A82: SIM | C82: =_xlfn.XLOOKUP(H82,RH!$D$2:$D$116,RH!$C$2:$C$116,"Terceiro") -> Terceiro | D82: =E82&" - "&F82 -> 2T - ROTA/5 | E82: 2T | F82: ROTA/5 | G82: MAIARA S. | H82: MAIARA SANTOS DE JESUS | I82: LIMGER | J82: BR4A006 | K82: 45665 | L82: =M82 & ", " & N82 & ", " & O82 & ", " & P82 & ", BAHIA" & ", BRASIL" -> RUA A, RUA ALEXANDRE BAHIA, N/A, GABRIELA, FEIRA DE SANTANA, BAHIA, BRASIL | M82: RUA A, RUA ALEXANDRE BAHIA | N82: N/A | O82: GABRIELA | P82: FEIRA DE SANTANA | Q82: RUA A, RUA ALEXANDRE BAHIA PROX: GINASIO DE ESPORTE | R82: GINASIO DE ESPORTE
A83: SIM | C83: =_xlfn.XLOOKUP(H83,RH!$D$2:$D$116,RH!$C$2:$C$116,"Terceiro") -> 81054406 | D83: =E83&" - "&F83 -> 2T - ROTA/2 | E83: 2T | F83: ROTA/2 | G83: MARCILIO. N | H83: MARCILIO NERI DE SOUZA | I83: PEPSICO | J83: =_xlfn.XLOOKUP(H83,RH!$D$2:$D$116,RH!$K$2:$K$116,"Terceiro") -> BR2A008 | K83: 45096 | L83: =M83 & ", " & N83 & ", " & O83 & ", " & P83 & ", BAHIA" & ", BRASIL" -> RUA CHARLETON, 339, SANTO ANTÔNIO DOS PRAZERES, FEIRA DE SANTANA, BAHIA, BRASIL | M83: RUA CHARLETON | N83: 339 | O83: SANTO ANTÔNIO DOS PRAZERES | P83: FEIRA DE SANTANA | Q83: RUA CHARLETON, N.º339, REF.: PROX.: AO COND.: ASTECA | R83: COND.: ASTECA
A84: SIM | C84: =_xlfn.XLOOKUP(H84,RH!$D$2:$D$116,RH!$C$2:$C$116,"Terceiro") -> 81033486 | D84: =E84&" - "&F84 -> 3T - ROTA/1 | E84: 3T | F84: ROTA/1 | G84: Marcio R. | H84: MARCIO REIS DE OLIVEIRA JUNIOR | I84: PEPSICO | J84: =_xlfn.XLOOKUP(H84,RH!$D$2:$D$116,RH!$K$2:$K$116,"Terceiro") -> BR1A294 | K84: 45019 | L84: =M84 & ", " & N84 & ", " & O84 & ", " & P84 & ", BAHIA" & ", BRASIL" -> Rua Nova Iguaçu, 114, CAMPO LIMPO, FEIRA DE SANTANA, BAHIA, BRASIL | M84: Rua Nova Iguaçu | N84: 114 | O84: CAMPO LIMPO | P84: FEIRA DE SANTANA | Q84: Rua Nova Iguaçu, N° 114 | R84: Em frente a Barbearia Jhon Mattos
A85: SIM | C85: =_xlfn.XLOOKUP(H85,RH!$D$2:$D$116,RH!$C$2:$C$116,"Terceiro") -> 80851934 | D85: =E85&" - "&F85 -> 1T - ROTA/3 | E85: 1T | F85: ROTA/3 | G85: MARCOS W. | H85: MARCOS WELINGTON VIANA MENEZES | I85: PEPSICO | J85: =_xlfn.XLOOKUP(H85,RH!$D$2:$D$116,RH!$K$2:$K$116,"Terceiro") -> BR1A009 | K85: 44382 | L85: =M85 & ", " & N85 & ", " & O85 & ", " & P85 & ", BAHIA" & ", BRASIL" -> RUA INTENDENTE ABDON, 380, QUEIMADINHA, FEIRA DE SANTANA, BAHIA, BRASIL | M85: RUA INTENDENTE ABDON | N85: 380 | O85: QUEIMADINHA | P85: FEIRA DE SANTANA | Q85: RUA INTENDENTE ABDON, 380 - EM FRENTE AO ABATEODOURO DA ROSY | R85: EM FRENTE AO ABATEODOURO DA ROSY
A86: SIM | C86: =_xlfn.XLOOKUP(H86,RH!$D$2:$D$116,RH!$C$2:$C$116,"Terceiro") -> 40201681 | D86: =E86&" - "&F86 -> 3T - ROTA/1 | E86: 3T | F86: ROTA/1 | G86: Marcus B. | H86: MARCUS VINICIUS DE OLIVEIRA BEIRAO | I86: PEPSICO | J86: =_xlfn.XLOOKUP(H86,RH!$D$2:$D$116,RH!$K$2:$K$116,"Terceiro") -> BR1A312 | K86: 41157 | L86: =M86 & ", " & N86 & ", " & O86 & ", " & P86 & ", BAHIA" & ", BRASIL" -> Rua Santa Luzia, 19, SÃO JOÃO, FEIRA DE SANTANA, BAHIA, BRASIL | M86: Rua Santa Luzia | N86: 19 | O86: SÃO JOÃO | P86: FEIRA DE SANTANA | Q86: Rua Santa Luzia, N° 19, Ponto de apanha | R86: Fundo do API
A87: SIM | C87: =_xlfn.XLOOKUP(H87,RH!$D$2:$D$116,RH!$C$2:$C$116,"Terceiro") -> Terceiro | D87: =E87&" - "&F87 -> 1T - ROTA/4 | E87: 1T | F87: ROTA/4 | G87: MARIA A. | H87: MARIA ANGELICA DO AMARAL BARBOSA | I87: LIMGER | J87: BR4A006 | K87: 45665 | L87: =M87 & ", " & N87 & ", " & O87 & ", " & P87 & ", BAHIA" & ", BRASIL" -> AV. SENADOR QUINTINO, 792, OLHOS D'ÁGUA, FEIRA DE SANTANA, BAHIA, BRASIL | M87: AV. SENADOR QUINTINO | N87: 792 | O87: OLHOS D'ÁGUA | P87: FEIRA DE SANTANA | Q87: AV. SENADOR QUINTINO, N°792 | R87: AV. SENADOR QUINTINO, N°792
A88: SIM | C88: =_xlfn.XLOOKUP(H88,RH!$D$2:$D$116,RH!$C$2:$C$116,"Terceiro") -> 81041744 | D88: =E88&" - "&F88 -> 1T - ROTA/8 | E88: 1T | F88: ROTA/8 | G88: MARIA V. | H88: MARIA VERBENA SANTOS LIMA | I88: PEPSICO | J88: =_xlfn.XLOOKUP(H88,RH!$D$2:$D$116,RH!$K$2:$K$116,"Terceiro") -> BR1A002 | K88: 45048 | L88: =M88 & ", " & N88 & ", " & O88 & ", " & P88 & ", BAHIA" & ", BRASIL" -> LOTEAMENTO AMARALINA - CAMINHO 10, CASA 25, GABRIELA, FEIRA DE SANTANA, BAHIA, BRASIL | M88: LOTEAMENTO AMARALINA - CAMINHO 10 | N88: CASA 25 | O88: GABRIELA | P88: FEIRA DE SANTANA | Q88: LOTEAMENTO AMARALINA - CAMINHO 10 CASA 25 - PROXIMO A MERCEARIA DISNORMAL DRINK'S | R88: PROXIMO A MERCEARIA DISNORMAL DRINK'S
A89: SIM | C89: =_xlfn.XLOOKUP(H89,RH!$D$2:$D$116,RH!$C$2:$C$116,"Terceiro") -> 81168348 | D89: =E89&" - "&F89 -> 1T - ROTA/3 | E89: 1T | F89: ROTA/3 | G89: MARIANA. S. | H89: MARIANA SILVA DOS ANJOS | I89: PEPSICO | J89: =_xlfn.XLOOKUP(H89,RH!$D$2:$D$116,RH!$K$2:$K$116,"Terceiro") -> BR1A010 | K89: 45509 | L89: =M89 & ", " & N89 & ", " & O89 & ", " & P89 & ", BAHIA" & ", BRASIL" -> RUA TOCANTINS, 423, SANTA MÔNICA, FEIRA DE SANTANA, BAHIA, BRASIL | M89: RUA TOCANTINS | N89: 423 | O89: SANTA MÔNICA | P89: FEIRA DE SANTANA | Q89: RUA TOCANTINS, N° 423 | R89: RUA TOCANTINS, N° 423
A90: SIM | C90: =_xlfn.XLOOKUP(H90,RH!$D$2:$D$116,RH!$C$2:$C$116,"Terceiro") -> 81150509 | D90: =E90&" - "&F90 -> 3T - ROTA/1 | E90: 3T | F90: ROTA/1 | G90: Mario.A | H90: MARIO ANDERSON SANTANA CARNEIRO | I90: PEPSICO | J90: =_xlfn.XLOOKUP(H90,RH!$D$2:$D$116,RH!$K$2:$K$116,"Terceiro") -> BR1A312 | K90: 45446 | L90: =M90 & ", " & N90 & ", " & O90 & ", " & P90 & ", BAHIA" & ", BRASIL" -> Rua Ibicui, 179, MANGABEIRA, FEIRA DE SANTANA, BAHIA, BRASIL | M90: Rua Ibicui | N90: 179 | O90: MANGABEIRA | P90: FEIRA DE SANTANA | Q90: Rua Ibicui, N° 179
A91: SIM | C91: =_xlfn.XLOOKUP(H91,RH!$D$2:$D$116,RH!$C$2:$C$116,"Terceiro") -> 81050388 | D91: =E91&" - "&F91 -> 2T - ROTA/5 | E91: 2T | F91: ROTA/5 | G91: MAXSUEL | H91: MAXSUEL COSTA DE SANT ANA | I91: PEPSICO | J91: =_xlfn.XLOOKUP(H91,RH!$D$2:$D$116,RH!$K$2:$K$116,"Terceiro") -> BR1A294 | K91: 45082 | L91: =M91 & ", " & N91 & ", " & O91 & ", " & P91 & ", BAHIA" & ", BRASIL" -> RUA CONSTITUINTE, 23, CAMPO LIMPO, FEIRA DE SANTANA, BAHIA, BRASIL | M91: RUA CONSTITUINTE | N91: 23 | O91: CAMPO LIMPO | P91: FEIRA DE SANTANA | Q91: RUA CONSTITUINTE N° 23, REF.: MATERIAL DE CONSTRUÇÃO CONSTRUFEIRA | R91: MATERIAL DE CONSTRUÇÃO CONSTRUFEIRA
A92: SIM | C92: =_xlfn.XLOOKUP(H92,RH!$D$2:$D$116,RH!$C$2:$C$116,"Terceiro") -> 40286011 | D92: =E92&" - "&F92 -> 1T - ROTA/7 | E92: 1T | F92: ROTA/7 | G92: MIRABELLE. N | H92: MIRABELE CERQUEIRA SANTANA NASCIMENTO | I92: PEPSICO | J92: =_xlfn.XLOOKUP(H92,RH!$D$2:$D$116,RH!$K$2:$K$116,"Terceiro") -> BR1A002 | K92: 41932 | L92: =M92 & ", " & N92 & ", " & O92 & ", " & P92 & ", BAHIA" & ", BRASIL" -> AO LADO DA IGREJA ASSEMBLEIA DE DEUS - R. JAILDO CUNHA DE JESUS, 69, CONCEIÇÃO DO JACUIPE, FEIRA DE SANTANA, BAHIA, BRASIL | M92: AO LADO DA IGREJA ASSEMBLEIA DE DEUS - R. JAILDO CUNHA DE JESUS | N92: 69 | O92: CONCEIÇÃO DO JACUIPE | P92: FEIRA DE SANTANA | Q92: AO LADO DA IGREJA ASSEMBLEIA DE DEUS - R. JAILDO CUNHA DE JESUS 69 - LOT. JOEL CAETANO | R92: LOT. JOEL CAETANO
A93: SIM | C93: =_xlfn.XLOOKUP(H93,RH!$D$2:$D$116,RH!$C$2:$C$116,"Terceiro") -> 80310115 | D93: =E93&" - "&F93 -> 1T - ROTA/3 | E93: 1T | F93: ROTA/3 | G93: MIRIAN. R | H93: MIRIAN RANGEL SILVA SANTANA | I93: PEPSICO | J93: =_xlfn.XLOOKUP(H93,RH!$D$2:$D$116,RH!$K$2:$K$116,"Terceiro") -> BR1A010 | K93: 44214 | L93: =M93 & ", " & N93 & ", " & O93 & ", " & P93 & ", BAHIA" & ", BRASIL" -> RUA TUIUCA, N/A, JOÃO PAULO, FEIRA DE SANTANA, BAHIA, BRASIL | M93: RUA TUIUCA | N93: N/A | O93: JOÃO PAULO | P93: FEIRA DE SANTANA | Q93: RUA TUIUCA - EM FRENTE A IGREJA BATISTA PALAVRA DA VIDA | R93: EM FRENTE A IGREJA BATISTA PALAVRA DA VIDA
A94: SIM | C94: =_xlfn.XLOOKUP(H94,RH!$D$2:$D$116,RH!$C$2:$C$116,"Terceiro") -> 40185829 | D94: =E94&" - "&F94 -> ADM - ROTA/4 | E94: ADM | F94: ROTA/4 | G94: NEY. R | H94: NEY DE OLIVEIRA RAMOS | I94: PEPSICO | J94: =_xlfn.XLOOKUP(H94,RH!$D$2:$D$116,RH!$K$2:$K$116,"Terceiro") -> BR2A032 | K94: 40948 | L94: =M94 & ", " & N94 & ", " & O94 & ", " & P94 & ", BAHIA" & ", BRASIL" -> RUA VASCO FILHO, 590, SERRARIA BRASIL, FEIRA DE SANTANA, BAHIA, BRASIL | M94: RUA VASCO FILHO | N94: 590 | O94: SERRARIA BRASIL | P94: FEIRA DE SANTANA | Q94: RUA VASCO FILHO | R94: PROX: AO PONTO DO FRANGO
A95: SIM | C95: =_xlfn.XLOOKUP(H95,RH!$D$2:$D$116,RH!$C$2:$C$116,"Terceiro") -> 40280015 | D95: =E95&" - "&F95 -> 1T - ROTA/6 | E95: 1T | F95: ROTA/6 | G95: NYLTON. J | H95: NYLTON SOUSA JUNIOR | I95: PEPSICO | J95: =_xlfn.XLOOKUP(H95,RH!$D$2:$D$116,RH!$K$2:$K$116,"Terceiro") -> BR2A032 | K95: 41869 | L95: =M95 & ", " & N95 & ", " & O95 & ", " & P95 & ", BAHIA" & ", BRASIL" -> COND. VIVACE PAPAGAIO, N/A, PAPAGAIO, FEIRA DE SANTANA, BAHIA, BRASIL | M95: COND. VIVACE PAPAGAIO | N95: N/A | O95: PAPAGAIO | P95: FEIRA DE SANTANA | Q95: COND. VIVACE PAPAGAIO | R95: COND. VIVACE PAPAGAIO
A96: SIM | C96: =_xlfn.XLOOKUP(H96,RH!$D$2:$D$116,RH!$C$2:$C$116,"Terceiro") -> 80851528 | D96: =E96&" - "&F96 -> 2T - ROTA/2 | E96: 2T | F96: ROTA/2 | G96: PAULO R. | H96: PAULO ROBERTO PALMEIRA DA SILVA | I96: PEPSICO | J96: =_xlfn.XLOOKUP(H96,RH!$D$2:$D$116,RH!$K$2:$K$116,"Terceiro") -> BR1A294 | K96: 44382 | L96: =M96 & ", " & N96 & ", " & O96 & ", " & P96 & ", BAHIA" & ", BRASIL" -> RUA 7, JARDIM EUROPA, 145, MANGABEIRA, FEIRA DE SANTANA, BAHIA, BRASIL | M96: RUA 7, JARDIM EUROPA | N96: 145 | O96: MANGABEIRA | P96: FEIRA DE SANTANA | Q96: RUA 7, Nº 145 JARDIM EUROPA, PONTO DE APANHA EM FRENTE A PRAÇA | R96: A PRAÇA
A97: SIM | C97: =_xlfn.XLOOKUP(H97,RH!$D$2:$D$116,RH!$C$2:$C$116,"Terceiro") -> 40302139 | D97: =E97&" - "&F97 -> ADM - ROTA/4 | E97: ADM | F97: ROTA/4 | G97: RAILANE. B | H97: RAILANE SANTOS BRITO | I97: PEPSICO | J97: =_xlfn.XLOOKUP(H97,RH!$D$2:$D$116,RH!$K$2:$K$116,"Terceiro") -> BR1A002 | K97: 42219 | L97: =M97 & ", " & N97 & ", " & O97 & ", " & P97 & ", BAHIA" & ", BRASIL" -> RUA DA PAZ, 107, BRASILIA, FEIRA DE SANTANA, BAHIA, BRASIL | M97: RUA DA PAZ | N97: 107 | O97: BRASILIA | P97: FEIRA DE SANTANA | Q97: RUA DA PAZ | R97: PROX: A QUITANDA DA MADEIRA
A98: SIM | C98: =_xlfn.XLOOKUP(H98,RH!$D$2:$D$116,RH!$C$2:$C$116,"Terceiro") -> 81081518 | D98: =E98&" - "&F98 -> 2T - ROTA/1 | E98: 2T | F98: ROTA/1 | G98: RAIMUNDO. O | H98: RAIMUNDO DE OLIVEIRA DUARTE | I98: PEPSICO | J98: =_xlfn.XLOOKUP(H98,RH!$D$2:$D$116,RH!$K$2:$K$116,"Terceiro") -> BR1A294 | K98: 45201 | L98: =M98 & ", " & N98 & ", " & O98 & ", " & P98 & ", BAHIA" & ", BRASIL" -> CONDOMINIO CENTRAL PARK, N/A, RUA NOVA, FEIRA DE SANTANA, BAHIA, BRASIL | M98: CONDOMINIO CENTRAL PARK | N98: N/A | O98: RUA NOVA | P98: FEIRA DE SANTANA | Q98: CONDOMINIO CENTRAL PARK | R98: CONDOMINIO CENTRAL PARK
A99: SIM | C99: =_xlfn.XLOOKUP(H99,RH!$D$2:$D$116,RH!$C$2:$C$116,"Terceiro") -> Terceiro | D99: =E99&" - "&F99 -> ADM - ROTA/7 | E99: ADM | F99: ROTA/7 | G99: REGILSON CARLOS O. | H99: REGILSON CARLOS OLIVEIRA | I99: LIMGER | J99: BR4A006 | K99: 45665 | L99: =M99 & ", " & N99 & ", " & O99 & ", " & P99 & ", BAHIA" & ", BRASIL" -> Rua do Mercado, N/A, HUMILDES, HUMILDES, BAHIA, BRASIL | M99: Rua do Mercado | N99: N/A | O99: HUMILDES | P99: HUMILDES | Q99: EM FRENTE AO MERCADO MUNICIPAL | R99: MERCADO MUNICIPAL
A100: SIM | C100: =_xlfn.XLOOKUP(H100,RH!$D$2:$D$116,RH!$C$2:$C$116,"Terceiro") -> 40175810 | D100: =E100&" - "&F100 -> 2T - ROTA/4 | E100: 2T | F100: ROTA/4 | G100: REGINALDO. C | H100: REGINALDO CERQUEIRA SANTIAGO | I100: PEPSICO | J100: =_xlfn.XLOOKUP(H100,RH!$D$2:$D$116,RH!$K$2:$K$116,"Terceiro") -> BR1A004 | K100: 40756 | L100: =M100 & ", " & N100 & ", " & O100 & ", " & P100 & ", BAHIA" & ", BRASIL" -> RUA TELES, 170, HUMILDES, HUMILDES, BAHIA, BRASIL | M100: RUA TELES | N100: 170 | O100: HUMILDES | P100: HUMILDES | Q100: RUA TELES, Nº 170, PONTO DE APANHA EM FRENTE AO ARMADINHO LN VARIEDADES | R100: ARMADINHO LN VARIEDADES
...

Sheet RH
A1: VICE PRESIDÊNCIA | B1: DIRETORIA | C1: GPID | D1: NOME | E1: Observação | F1: CODIGOCARGO | G1: CARGO | H1: Position Code | I1: CODLOCAL | J1: DESCLOCAL | K1: CODCCUSTO | L1: DESCCCUSTO | M1: DATAADMISSAO | N1: ANIVERSÁRIO | O1: Horário | P1: GPID - GESTOR IMEDIATO | Q1: GESTOR IMEDIATO | R1: EMAIL CORPORATIVO | S1: STATUS | T1: SETOR
A2: Total Operacoes | B2: Manufatura Nutrition | C2: 40277251 | D2: ELIOMAR CARVALHO DA PAIXAO | E2: Fábrica Feira de Santana | F2: 5031 | G2: OPERADOR MULTIFUNCIONAL | H2: P50540268 | I2: 20009 | J2: FÁBRICA FEIRA DE SANTANA | K2: BR1A010 | L2: PRODUCAO MAGICO BA | M2: 41792 | N2: 13/7 | O2: 06:00 10:00 11:10 14:30 | P2: 40172715 | Q2: ALINE SOARES ANDRADE GAVAZZA | R2: eliomar.paixao@pepsico.com | S2: A | T2: {=IF(_xlfn.XLOOKUP(1, (Tabela25[CARGO] = Tabela2[[#This Row],[CARGO]]) * (Tabela25[CC] = Tabela2[[#This Row],[DESCCCUSTO]]), Tabela25[SETOR/EMPRESA], "INSERIR SETOR")="", "INSERIR SETOR", _xlfn.XLOOKUP(1, (Tabela25[CARGO] = Tabela2[[#This Row],[CARGO]]) * (Tabela25[CC] = Tabela2[[#This Row],[DESCCCUSTO]]), Tabela25[SETOR/EMPRESA], "INSERIR SETOR"))} -> 0
A3: Total Operacoes | B3: Manufatura Nutrition | C3: 40213379 | D3: VALLENO LIMA SENA | E3: Fábrica Feira de Santana | F3: 5031 | G3: OPERADOR MULTIFUNCIONAL | H3: P00190666 | I3: 20009 | J3: FÁBRICA FEIRA DE SANTANA | K3: BR1A010 | L3: PRODUCAO MAGICO BA | M3: 41372 | N3: 12/8 | O3: 06:00 10:00 11:10 14:30 | P3: 40172715 | Q3: ALINE SOARES ANDRADE GAVAZZA | R3: VALLENO.SENA@pepsico.com | S3: A | T3: {=IF(_xlfn.XLOOKUP(1, (Tabela25[CARGO] = Tabela2[[#This Row],[CARGO]]) * (Tabela25[CC] = Tabela2[[#This Row],[DESCCCUSTO]]), Tabela25[SETOR/EMPRESA], "INSERIR SETOR")="", "INSERIR SETOR", _xlfn.XLOOKUP(1, (Tabela25[CARGO] = Tabela2[[#This Row],[CARGO]]) * (Tabela25[CC] = Tabela2[[#This Row],[DESCCCUSTO]]), Tabela25[SETOR/EMPRESA], "INSERIR SETOR"))} -> 0
A4: Total Operacoes | B4: Manufatura Nutrition | C4: 40285831 | D4: ELIAS MOREIRA DA FONSECA | E4: Fábrica Feira de Santana | F4: 5031 | G4: OPERADOR MULTIFUNCIONAL | H4: P00190669 | I4: 20009 | J4: FÁBRICA FEIRA DE SANTANA | K4: BR1A010 | L4: PRODUCAO MAGICO BA | M4: 41925 | N4: 17/6 | O4: 06:00 10:00 11:10 14:30 | P4: 40172715 | Q4: ALINE SOARES ANDRADE GAVAZZA | R4: ELIAS.DAFONSECA@pepsico.com | S4: A | T4: {=IF(_xlfn.XLOOKUP(1, (Tabela25[CARGO] = Tabela2[[#This Row],[CARGO]]) * (Tabela25[CC] = Tabela2[[#This Row],[DESCCCUSTO]]), Tabela25[SETOR/EMPRESA], "INSERIR SETOR")="", "INSERIR SETOR", _xlfn.XLOOKUP(1, (Tabela25[CARGO] = Tabela2[[#This Row],[CARGO]]) * (Tabela25[CC] = Tabela2[[#This Row],[DESCCCUSTO]]), Tabela25[SETOR/EMPRESA], "INSERIR SETOR"))} -> 0
A5: Total Operacoes | B5: Manufatura Nutrition | C5: 80310115 | D5: MIRIAN RANGEL SILVA SANTANA | E5: Fábrica Feira de Santana | F5: 5179 | G5: AUXILIAR DE PRODUCAO | H5: P00073945 | I5: 20009 | J5: FÁBRICA FEIRA DE SANTANA | K5: BR1A010 | L5: PRODUCAO MAGICO BA | M5: 44214 | N5: 30/6 | O5: 06:00 10:00 11:10 14:30 | P5: 40172715 | Q5: ALINE SOARES ANDRADE GAVAZZA | R5: MIRIAN.SANTANA@pepsico.com | S5: A | T5: {=IF(_xlfn.XLOOKUP(1, (Tabela25[CARGO] = Tabela2[[#This Row],[CARGO]]) * (Tabela25[CC] = Tabela2[[#This Row],[DESCCCUSTO]]), Tabela25[SETOR/EMPRESA], "INSERIR SETOR")="", "INSERIR SETOR", _xlfn.XLOOKUP(1, (Tabela25[CARGO] = Tabela2[[#This Row],[CARGO]]) * (Tabela25[CC] = Tabela2[[#This Row],[DESCCCUSTO]]), Tabela25[SETOR/EMPRESA], "INSERIR SETOR"))} -> 0
A6: Total Operacoes | B6: Manufatura Nutrition | C6: 80851941 | D6: ELIANA DE ALMEIDA OLIVEIRA | E6: Fábrica Feira de Santana | F6: 5179 | G6: AUXILIAR DE PRODUCAO | H6: P00073627 | I6: 20009 | J6: FÁBRICA FEIRA DE SANTANA | K6: BR1A010 | L6: PRODUCAO MAGICO BA | M6: 44382 | N6: 3/4 | O6: 06:00 10:00 11:10 14:30 | P6: 40172715 | Q6: ALINE SOARES ANDRADE GAVAZZA | R6: ELIANA.OLIVEIRA@pepsico.com | S6: A | T6: {=IF(_xlfn.XLOOKUP(1, (Tabela25[CARGO] = Tabela2[[#This Row],[CARGO]]) * (Tabela25[CC] = Tabela2[[#This Row],[DESCCCUSTO]]), Tabela25[SETOR/EMPRESA], "INSERIR SETOR")="", "INSERIR SETOR", _xlfn.XLOOKUP(1, (Tabela25[CARGO] = Tabela2[[#This Row],[CARGO]]) * (Tabela25[CC] = Tabela2[[#This Row],[DESCCCUSTO]]), Tabela25[SETOR/EMPRESA], "INSERIR SETOR"))} -> 0
A7: Total Operacoes | B7: Manufatura Nutrition | C7: 80873151 | D7: LUIZ EDUARDO DE OLIVEIRA SANTOS | E7: Fábrica Feira de Santana | F7: 5031 | G7: OPERADOR MULTIFUNCIONAL | H7: P00190670 | I7: 20009 | J7: FÁBRICA FEIRA DE SANTANA | K7: BR1A010 | L7: PRODUCAO MAGICO BA | M7: 44459 | N7: 24/1 | O7: 06:00 10:00 11:10 14:30 | P7: 40172715 | Q7: ALINE SOARES ANDRADE GAVAZZA | R7: LUIZEDUARDO.SANTOS@pepsico.com | S7: A | T7: {=IF(_xlfn.XLOOKUP(1, (Tabela25[CARGO] = Tabela2[[#This Row],[CARGO]]) * (Tabela25[CC] = Tabela2[[#This Row],[DESCCCUSTO]]), Tabela25[SETOR/EMPRESA], "INSERIR SETOR")="", "INSERIR SETOR", _xlfn.XLOOKUP(1, (Tabela25[CARGO] = Tabela2[[#This Row],[CARGO]]) * (Tabela25[CC] = Tabela2[[#This Row],[DESCCCUSTO]]), Tabela25[SETOR/EMPRESA], "INSERIR SETOR"))} -> 0
A8: Total Operacoes | B8: Manufatura Nutrition | C8: 80997603 | D8: CLEIDIANE DE OLIVEIRA LIMA | E8: Fábrica Feira de Santana | F8: 5179 | G8: AUXILIAR DE PRODUCAO | H8: P00190680 | I8: 20009 | J8: FÁBRICA FEIRA DE SANTANA | K8: BR1A010 | L8: PRODUCAO MAGICO BA | M8: 44872 | N8: 27/3 | O8: 06:00 10:00 11:10 14:30 | P8: 40172715 | Q8: ALINE SOARES ANDRADE GAVAZZA | R8: CLEIDIANE.LIMA@pepsico.com | S8: A | T8: {=IF(_xlfn.XLOOKUP(1, (Tabela25[CARGO] = Tabela2[[#This Row],[CARGO]]) * (Tabela25[CC] = Tabela2[[#This Row],[DESCCCUSTO]]), Tabela25[SETOR/EMPRESA], "INSERIR SETOR")="", "INSERIR SETOR", _xlfn.XLOOKUP(1, (Tabela25[CARGO] = Tabela2[[#This Row],[CARGO]]) * (Tabela25[CC] = Tabela2[[#This Row],[DESCCCUSTO]]), Tabela25[SETOR/EMPRESA], "INSERIR SETOR"))} -> 0
A9: Total Operacoes | B9: Manufatura Nutrition | C9: 81168348 | D9: MARIANA SILVA DOS ANJOS | E9: Fábrica Feira de Santana | F9: 5179 | G9: AUXILIAR DE PRODUCAO | H9: P50838653 | I9: 20009 | J9: FÁBRICA FEIRA DE SANTANA | K9: BR1A010 | L9: PRODUCAO MAGICO BA | M9: 45509 | N9: 3/3 | O9: 06:00 10:00 11:10 14:30 | P9: 40172715 | Q9: ALINE SOARES ANDRADE GAVAZZA | R9: MARIANA.DOSANJOS@pepsico.com | S9: A | T9: {=IF(_xlfn.XLOOKUP(1, (Tabela25[CARGO] = Tabela2[[#This Row],[CARGO]]) * (Tabela25[CC] = Tabela2[[#This Row],[DESCCCUSTO]]), Tabela25[SETOR/EMPRESA], "INSERIR SETOR")="", "INSERIR SETOR", _xlfn.XLOOKUP(1, (Tabela25[CARGO] = Tabela2[[#This Row],[CARGO]]) * (Tabela25[CC] = Tabela2[[#This Row],[DESCCCUSTO]]), Tabela25[SETOR/EMPRESA], "INSERIR SETOR"))} -> 0
A10: Total Operacoes | B10: Manufatura Nutrition | C10: 81252475 | D10: TIAGO SANTOS VENAS | E10: Fábrica Feira de Santana | F10: 5179 | G10: AUXILIAR DE PRODUCAO | H10: P00073640 | I10: 20009 | J10: FÁBRICA FEIRA DE SANTANA | K10: BR1A010 | L10: PRODUCAO MAGICO BA | M10: 46034 | N10: 10/6 | O10: 14:20 18:00 19:10 22:45 | P10: 40172715 | Q10: ALINE SOARES ANDRADE GAVAZZA | R10: tiagovenas964@gmail.com | S10: A | T10: {=IF(_xlfn.XLOOKUP(1, (Tabela25[CARGO] = Tabela2[[#This Row],[CARGO]]) * (Tabela25[CC] = Tabela2[[#This Row],[DESCCCUSTO]]), Tabela25[SETOR/EMPRESA], "INSERIR SETOR")="", "INSERIR SETOR", _xlfn.XLOOKUP(1, (Tabela25[CARGO] = Tabela2[[#This Row],[CARGO]]) * (Tabela25[CC] = Tabela2[[#This Row],[DESCCCUSTO]]), Tabela25[SETOR/EMPRESA], "INSERIR SETOR"))} -> 0
A11: Total Operacoes | B11: Manufatura Nutrition | C11: 40285860 | D11: ADEMILDES DA CONCEICAO | E11: Fábrica Feira de Santana | F11: 5031 | G11: OPERADOR MULTIFUNCIONAL | H11: P00190665 | I11: 20009 | J11: FÁBRICA FEIRA DE SANTANA | K11: BR1A009 | L11: PRODUCAO TODDY BA | M11: 41925 | N11: 1/8 | O11: 06:00 10:00 11:00 14:20 | P11: 40172715 | Q11: ALINE SOARES ANDRADE GAVAZZA | R11: Ademildes.DaConceicao1@pepsico.com | S11: A | T11: {=IF(_xlfn.XLOOKUP(1, (Tabela25[CARGO] = Tabela2[[#This Row],[CARGO]]) * (Tabela25[CC] = Tabela2[[#This Row],[DESCCCUSTO]]), Tabela25[SETOR/EMPRESA], "INSERIR SETOR")="", "INSERIR SETOR", _xlfn.XLOOKUP(1, (Tabela25[CARGO] = Tabela2[[#This Row],[CARGO]]) * (Tabela25[CC] = Tabela2[[#This Row],[DESCCCUSTO]]), Tabela25[SETOR/EMPRESA], "INSERIR SETOR"))} -> 0
A12: Total Operacoes | B12: Manufatura Nutrition | C12: 80084668 | D12: SILVIO FERNANDO DE CARVALHO VASCONCELOS | E12: Fábrica Feira de Santana | F12: 5179 | G12: AUXILIAR DE PRODUCAO | H12: P00107081 | I12: 20009 | J12: FÁBRICA FEIRA DE SANTANA | K12: BR1A009 | L12: PRODUCAO TODDY BA | M12: 43024 | N12: 11/2 | O12: 06:00 10:00 11:10 14:30 | P12: 40172715 | Q12: ALINE SOARES ANDRADE GAVAZZA | R12: SILVIOFERNANDO.VASCONCELOS@pepsico.com | S12: A | T12: {=IF(_xlfn.XLOOKUP(1, (Tabela25[CARGO] = Tabela2[[#This Row],[CARGO]]) * (Tabela25[CC] = Tabela2[[#This Row],[DESCCCUSTO]]), Tabela25[SETOR/EMPRESA], "INSERIR SETOR")="", "INSERIR SETOR", _xlfn.XLOOKUP(1, (Tabela25[CARGO] = Tabela2[[#This Row],[CARGO]]) * (Tabela25[CC] = Tabela2[[#This Row],[DESCCCUSTO]]), Tabela25[SETOR/EMPRESA], "INSERIR SETOR"))} -> 0
A13: Total Operacoes | B13: Manufatura Nutrition | C13: 80851934 | D13: MARCOS WELINGTON VIANA MENEZES | E13: Fábrica Feira de Santana | F13: 5031 | G13: OPERADOR MULTIFUNCIONAL | H13: P00190668 | I13: 20009 | J13: FÁBRICA FEIRA DE SANTANA | K13: BR1A009 | L13: PRODUCAO TODDY BA | M13: 44382 | N13: 25/1 | O13: 06:00 10:00 11:10 14:30 | P13: 40172715 | Q13: ALINE SOARES ANDRADE GAVAZZA | R13: MARCOS.MENEZES@pepsico.com | S13: A | T13: {=IF(_xlfn.XLOOKUP(1, (Tabela25[CARGO] = Tabela2[[#This Row],[CARGO]]) * (Tabela25[CC] = Tabela2[[#This Row],[DESCCCUSTO]]), Tabela25[SETOR/EMPRESA], "INSERIR SETOR")="", "INSERIR SETOR", _xlfn.XLOOKUP(1, (Tabela25[CARGO] = Tabela2[[#This Row],[CARGO]]) * (Tabela25[CC] = Tabela2[[#This Row],[DESCCCUSTO]]), Tabela25[SETOR/EMPRESA], "INSERIR SETOR"))} -> 0
... A116: Total Operacoes | B116: Manufatura | C116: 80304771 | D116: KATARYNNA SANTOS DE ARAUJO | E116: Fábrica Feira de Santana | F116: 2193 | G116: ANALISTA DE MELHORIA CONTINUA SR | H116: P50569559 | I116: 20009 | J116: FÁBRICA FEIRA DE SANTANA | K116: BR1A054 | L116: ATB & LSS MANUF PROD | M116: 44179 | N116: 30/7 | O116: 07:30 12:00 13:00 17:18 | P116: 40050609 | Q116: ROSIMAYRE DA SILVA SOUSA | R116: katarynna.araujo@pepsico.com | S116: A | T116: {=IF(_xlfn.XLOOKUP(1, (Tabela25[CARGO] = Tabela2[[#This Row],[CARGO]]) * (Tabela25[CC] = Tabela2[[#This Row],[DESCCCUSTO]]), Tabela25[SETOR/EMPRESA], "INSERIR SETOR")="", "INSERIR SETOR", _xlfn.XLOOKUP(1, (Tabela25[CARGO] = Tabela2[[#This Row],[CARGO]]) * (Tabela25[CC] = Tabela2[[#This Row],[DESCCCUSTO]]), Tabela25[SETOR/EMPRESA], "INSERIR SETOR"))} -> 0

Sheet SETORES E EMPRESAS
A1: CC | B1: CARGO | C1: SETOR/EMPRESA
A2: ASSISTENTE LOGISTICA SR | B2: ALM INSUMOS BA | C2: ALMOXARIFADO / EXPEDIÇÃO
A3: ALMOXARIFE | B3: ALMOXARIFADO PECAS | C3: ALMOXARIFADO
A4: ANALISTA DE MELHORIA CONTINUA SR | B4: ATB & LSS MANUF PROD
A5: AUXILIAR DE PRODUCAO | B5: COMBI 24000 | C5: TODDYNHO
A6: OPERADOR MULTIFUNCIONAL | B6: COMBI 24000 | C6: TODDYNHO
A7: ANALISTA CONTROLADORIA PL | B7: CONTR FABR ITU MOH
A8: CWBEM | B8: =Tabela25[[#This Row],[CARGO]] -> CWBEM | C8: =Tabela25[[#This Row],[CARGO]] -> CWBEM
A9: ASSISTENTE LOGISTICA SR | B9: EXP E ARMAZENS FOODS | C9: EXPEDIÇÃO
A10: GERENTE DISTRIBUICAO | B10: EXP E ARMAZENS FOODS | C10: EXPEDIÇÃO
A11: SUPERVISOR DE DISTRIBUICAO A | B11: EXP E ARMAZENS FOODS | C11: EXPEDIÇÃO
A12: ANALISTA DE PCM PL | B12: GERENCIA MANUTENCAO | C12: MANUTENÇÃO
A13: COORDENADOR DE UTILIDADES | B13: GERENCIA MANUTENCAO | C13: MANUTENÇÃO
A14: ENGENHEIRO PL | B14: GERENCIA MANUTENCAO | C14: MANUTENÇÃO
A15: GERENTE MANUTENCAO | B15: GERENCIA MANUTENCAO | C15: MANUTENÇÃO
A16: TECNICO ELETROMECANICO II | B16: GERENCIA MANUTENCAO | C16: MANUTENÇÃO
A17: TECNICO ESPECIALISTA | B17: GERENCIA MANUTENCAO | C17: MANUTENÇÃO
A18: TECNICO MECANICO II | B18: GERENCIA MANUTENCAO | C18: MANUTENÇÃO
A19: TECNICO MECANICO III | B19: GERENCIA MANUTENCAO | C19: MANUTENÇÃO
A20: GERENTE DE MANUFATURA | B20: GERENCIA PRODUCAO BA
A21: OPERADOR MULTIFUNCIONAL ESPECIALIZADO | B21: GERENCIA PRODUCAO BA
A22: GERENTE DE MANUFATURA | B22: GERENTE DE PLANTA BA
A23: LIMGER | B23: =Tabela25[[#This Row],[CARGO]] -> LIMGER | C23: =Tabela25[[#This Row],[CARGO]] -> LIMGER
A24: MANPOWER | B24: =Tabela25[[#This Row],[CARGO]] -> MANPOWER | C24: =Tabela25[[#This Row],[CARGO]] -> MANPOWER
A25: OPERADOR UTILIDADES | B25: MANUTENCAO UTILIDADE | C25: MANUTENÇÃO
A26: AUXILIAR DE PRODUCAO | B26: PREPARACAO ESTERELIZ | C26: TODDYNHO
A27: OPERADOR MULTIFUNCIONAL | B27: PREPARACAO ESTERELIZ | C27: TODDYNHO
A28: OPERADOR MULTIFUNCIONAL ESPECIALIZADO | B28: PREPARACAO ESTERELIZ | C28: TODDYNHO
A29: AUXILIAR DE PRODUCAO | B29: PRODUCAO MAGICO BA | C29: TODDYNHO
A30: OPERADOR MULTIFUNCIONAL | B30: PRODUCAO MAGICO BA | C30: TODDYNHO
A31: AUXILIAR DE PRODUCAO | B31: PRODUCAO MISTURA BA | C31: TODDYNHO
A32: OPERADOR MULTIFUNCIONAL | B32: PRODUCAO MISTURA BA | C32: TODDY
A33: AUXILIAR DE PRODUCAO | B33: PRODUCAO TODDY BA | C33: TODDY
A34: OPERADOR MULTIFUNCIONAL | B34: PRODUCAO TODDY BA | C34: TODDY
A35: ANALISTA DE QUALIDADE JR | B35: QUALIDADE CHOCOLATE | C35: QUALIDADE
A36: COORDENADOR DE QUALIDADE | B36: QUALIDADE CHOCOLATE | C36: QUALIDADE
... A40: TECNICO SEGURANCA DO TRABALHO II | B40: SEG TRAB ENFERMAGEM | C40: EHS

Sheet INATIVOS
A1: GPID | B1: NOME | C1: EMPRESA | D1: DATA ADMISSÃO | E1: DATA SAIDA DO FRETADO | F1: MOTIVO | G1: LOGRADOURO | H1: Nº | I1: BAIRRO | J1: CIDADE | K1: TURNO | L1: PONTO DE EMBARQUE | M1: REFERÊNCIA | N1: TELEFONE
A2: 80228814 | B2: BRUNA MORENO DA SILVA | C2: PEPSICO | D2: N | E2: 44196 | F2: DESLIGAMENTO | G2: VIA PEDESTRE 47 | H2: 63 | I2: VIVEIROS | J2: FEIRA DE SANTANA | K2: 1º | M2: EM FRENTE A IGREJA QUADRANGULAR | N2: N
A3: 40177280 | B3: MONICA SANTANA SANTOS RODRIGUES | C3: PEPSICO | D3: N | E3: 44773 | F3: DESLIGAMENTO | G3: ESTRADA DO FRANCÊS | H3: 300 | I3: PAPAGAIO | J3: FEIRA DE SANTANA | K3: ADM | L3: COND: RESIDENCIAL NOVITÁ | N3: N
A4: 40257896 | B4: IZAEL DOS SANTOS FERREIRA | C4: PEPSICO | D4: N | E4: 44774 | F4: DESLIGAMENTO | G4: AV. GETULIO VARGAS | H4: N | I4: CONCEIÇÃO DO JACUIPE | J4: CONCEIÇÃO DO JACUIPE | K4: 2º | M4: EM FRENTE AO HOSPITAL ACM | N4: N
A5: 80013703 | B5: TIAGO MENEZES CONCEIÇÃO ANCHIETA | C5: PEPSICO | D5: N | E5: 44866 | F5: DESLIGAMENTO | G5: RUA SANTO AMARO | H5: 266 | I5: CHACARA SÃO COSME | J5: FEIRA DE SANTANA | K5: 1º | L5: EM FRENTE AO ASSISTENCIAL CHÁCARA SÃO COSME | N5: N
A6: 40286072 | B6: EVILÁSIO NELSON CORREIA CARVALHO JUNIOR | C6: PEPSICO | D6: N | E6: 44872 | F6: DESLIGAMENTO | G6: RUA ANTONIO FERNANDEZ DE OLIVEIRA | H6: 85 | I6: SÃO GONÇALO DOS CAMPOS | J6: SÃO GONÇALO DOS CAMPOS | K6: 1º | M6: PROX: A PADARIA (ART & PÃO) | N6: N
A7: 40201920 | B7: ELIENE CERQUEIRA DO CARMO | C7: PEPSICO | D7: N | E7: 44907 | F7: MUDANÇA PARA ROTEIRO ANTIGO | G7: JOÃO DURVAL | H7: N | I7: CENTRO | J7: FEIRA DE SANTANA | K7: ADM | M7: EM FRENTE A CASTELLE KIDS | N7: N
A8: 40216113 | B8: CASSIO MARTINS DA SILVA | C8: PEPSICO | D8: 10/06/2013 | E8: 44908 | F8: DESLIGAMENTO | G8: RUA POLITEAMA | H8: N | I8: SÚBAE | J8: FEIRA DE SANTANA | K8: 1º | M8: EM FRENTE AO COND FONTE DAS AGUÁS ( PROX A UNEF ) | N8: N
A9: 40201094 | B9: FABRICIO CARVALHO DE JESUS MAGALHÃES | C9: PEPSICO | D9: 22/08/2012 | E9: 44908 | F9: DESLIGAMENTO | G9: RUA VISCONDE DE MAUA | H9: N | I9: ESTAÇÃO NOVA | J9: FEIRA DE SANTANA | K9: 1º | M9: EM FRENTE AO SUPERMECADO MERCANTIL ORIENTE | N9: N
A10: NA | B10: JAMILE PEREIRA | C10: CWBEM | D10: N | E10: 44928 | F10: DESLIGAMENTO | G10: AVENIDA JOÃO DURVAL | H10: N | I10: BRASILIA | J10: FEIRA DE SANTANA | K10: ADM | M10: EM FRENTE A PETHORSE RAÇÕES | N10: N
A11: NA | B11: MAIARA ARGOLO NEGROMONTE | C11: RANDSTAD | D11: N | E11: 44937 | F11: DESLIGAMENTO | G11: RUA TUIUTI | H11: 270 | I11: CONCEIÇÃO | J11: FEIRA DE SANTANA | K11: 2º | N11: (75)9-9263-0006
A12: NA | B12: ELIAS BATISTA DOS SANTOS | C12: PEPSICO | E12: 44938 | F12: SEM COBERTURA DE BAIRRO | G12: RUA AV. FROTA | I12: MURILO LEITE | J12: SÃO GONÇALO | K12: ADM | L12: CLINICA DE MOTO | N12: N
A13: 80107261 | B13: VINICIUS SOUZA CORDEIRO | C13: PEPSICO | D13: 19/03/2018 | E13: 44958 | F13: MUDANÇA PARA VT | G13: RUA E 1 | H13: 7 | I13: FEIRA X | J13: FEIRA DE SANTANA | K13: ADM | M13: ESCOLA MANOEL GREGORIO | N13: N
A14: 80159517 | B14: DAIANE SILVA XAVIER | C14: PEPSICO | D14: 17/12/2018 | E14: 44958 | F14: MUDANÇA PARA VT | G14: RUA CAMBORIU | H14: 50 | I14: SIM | J14: FEIRA DE SANTANA | K14: ADM | L14: EM FRENTE CONCESSIONARIA CHERY, ATRÁS SHOPPIN AVENIDA | N14: N
A15: 40262398 | B15: LARISSA MAGALHAES DOREA MARTINS | C15: PEPSICO | D15: 17/03/2014 | E15: 44958 | F15: MUDANÇA PARA VT | G15: RUA CAJUEIRO | H15: 18 | I15: CONCEIÇÃO | J15: FEIRA DE SANTANA | K15: ADM | N15: N
A16: 40296432 | B16: ANNA RUBIA LOBO FERREIRA GOMES | C16: PEPSICO | D16: 04/05/2015 | E16: 44958 | F16: MUDANÇA PARA VT | G16: RUA TEREZINHA MAGALHÃES | H16: N | I16: FRATERNIDADE | J16: FEIRA DE SANTANA | K16: ADM | M16: EM FRENTE BAR DA KAISER | N16: N
A17: 40286567 | B17: SILVIO ROBSON AMARAL DOS SANTOS | C17: PEPSICO | D17: 03/11/2014 | E17: 44963 | F17: DESLIGAMENTO | G17: RUA COCOROBÓ | H17: 82 | I17: MANGABEIRA | J17: FEIRA DE SANTANA | K17: 1º | M17: PROX: AO COND: IGUATEMI 03 | N17: N
A18: 80155954 | B18: THAIS LIMA DOS SANTOS | C18: PEPSICO | D18: 19/11/2018 | E18: 44963 | F18: DESLIGAMENTO | G18: RUA RIO GRANDE | H18: 29 | I18: QUEIMADINHA | J18: FEIRA DE SANTANA | K18: 1º | L18: PONTO DE APANHA EM FRENTE AO POSTO DE SAÚDE | N18: N
A19: 80321032 | B19: JOELMA COSTA DA CRUZ NASCIMENTO | C19: PEPSICO | D19: 15/03/2021 | E19: 44963 | F19: DESLIGAMENTO | G19: RUA QUIRINÓPOLIS | H19: 259 | I19: BRASILIA | J19: FEIRA DE SANTANA | K19: 1º | M19: EM FRENTE A LOJA TURMA SARA | N19: N
A20: NA | B20: EDNEI CARDOSO DE OLIVEIRA | C20: RANDSTAD | D20: N | E20: 44967 | F20: DESLIGAMENTO | G20: RUA MINAS AZUIS | H20: 40 | I20: TOMBA | J20: FEIRA DE SANTANA | K20: 1º | L20: ESCOLA EDUCANDÁRIO UNIÃO DA VITORIA | N20: 9 8156 - 03001
A21: NA | B21: ALISSON SANTOS BARRETO | C21: RANDSTAD | D21: N | E21: 44972 | F21: DESLIGAMENTO | G21: RUA SÃO ROQUE | H21: 1853 | I21: PARQUE JETULIO | J21: FEIRA DE SANTANA | K21: AMD EPC | M21: REF: POSTO MENOR PREÇO | N21: (75)9-8839-9220
A22: NA | B22: LUIS CARLOS DOS SANTOS DE JESUS | C22: RANDSTAD | D22: N | E22: 44972 | F22: DESLIGAMENTO | G22: RUA SÃO FRANCISCO | H22: 20 | I22: FEIRA VII | J22: FEIRA DE SANTANA | K22: 1º | M22: CONJ HILDES FERREIRA | N22: (75)9 -8819 - 1825
A23: NA | B23: ROMARIO ARAUJO SANTANA | C23: RANDSTAD | D23: N | E23: 44972 | F23: DESLIGAMENTO | G23: RUA DESEMBARGADOR FILINTO BASTO | H23: 23 | I23: CENTRO | J23: FEIRA DE SANTANA | K23: AMD EPC | M23: PROX: A PADARIA PADRE OVIDIO | N23: N
A24: 40185180 | B24: PAULO HENRIQUE CORREIA OLIVEIRA | C24: PEPSICO | D24: 16/01/2012 | E24: 44972 | F24: DESLIGAMENTO | G24: RUA ITAPETINGA | H24: 471 | I24: SIM | J24: FEIRA DE SANTANA | K24: 3º | M24: PROX: A IGREJA, REF: COND: RESERVA REAL | N24: N
A25: NA | B25: AURINO AMORIM RODRIGUES | C25: GRI | D25: N | E25: 44981 | F25: DESLIGAMENTO | G25: RUA SALGADEIRA | H25: N | I25: HUMILDES | J25: FEIRA DE SANTANA | K25: ADM | L25: EM FRENTE A LOJA DE MOVEIS DEUS É FIEL | N25: N
A26: NA | B26: EZEQUIEL LIMA DOS SANTOS | C26: GRI | D26: N | E26: 44981 | F26: DESLIGAMENTO | G26: RUA S | H26: N | I26: AVIARIO | J26: FEIRA DE SANTANA | K26: 1º | L26: EM FRENTE AO MERCADINHO COSME E DAMIÃO | N26: (75)9-8240-6561
A27: NA | B27: ISABELLA DOS SANTOS DE OLIVEIRA | C27: GRI | D27: N | E27: 44981 | F27: DESLIGAMENTO | G27: RUA LOUDES MARIA DA SILVA | H27: N | I27: MANGABEIRA | J27: FEIRA DE SANTANA | K27: ADM | N27: N
A28: NA | B28: JOSÉ RAMOS DOS SANTOS | C28: GRI | D28: N | E28: 44981 | F28: DESLIGAMENTO | G28: RUA MILTON486 | H28: N | I28: AMELIA RODRIGUES (ITAPICURU) | J28: AMELIA RODRIGUES (ITAPICURU) | K28: ADM | L28: ATRÁS DO FORUM DE A. RODRIGUES | N28: N
A29: NA | B29: MARIVAN NASCIMENTO | C29: GRI | D29: N | E29: 44981 | F29: DESLIGAMENTO | G29: RUA RIO ITAPEMIRIM | H29: N | I29: BRASILIA | J29: FEIRA DE SANTANA | K29: 2º | L29: EM FRENTE A DROGARIA DO BAIRRO | N29: N
A30: 40296432 | B30: ANNA RUBIA LOBO FERREIRA GOMES | C30: PEPSICO | D30: 04/05/2015 | E30: 44984 | F30: FALECIMENTO | G30: RUA TEREZINHA MAGALHÃES | H30: N | I30: FRATERNIDADE | J30: FEIRA DE SANTANA | K30: 2º | M30: EM FRENTE BAR DA KAISER | N30: N
A31: NA | B31: MARCELA BARBARA PEREIRA DE JESUS | C31: CWBEM | D31: N | E31: 44998 | F31: DESLIGAMENTO | G31: RUA SÃO PEDRO DOS DERROS | H31: 7 | I31: SIM | J31: FEIRA DE SANTANA | K31: ADM | N31: 9 8142 - 7843
A32: NA | B32: ELAINE DA CRUZ COSTA BARBOSA | C32: RANDSTAD | D32: N | E32: 44998 | F32: DESLIGAMENTO | G32: QUINTA DO SOL VILLE 1 | H32: N | I32: PARQUE IPÊ | J32: FEIRA DE SANTANA | K32: AMD EPC | N32: (75)9-9204 -2511
A33: NA | B33: ZOENE DE JESUS | C33: RANDSTAD | D33: N | E33: 44998 | F33: DESLIGAMENTO | G33: RUA HONORATO BONFIM | H33: 635 | I33: BRASILIA | J33: FEIRA DE SANTANA | K33: 2º | L33: RPOX: A IGREJA ASSEMBLEIA DE DEUS | N33: (75)9-8169 - 2968
A34: NA | B34: RICARDO DA SILVA SANTOS | C34: RANDSTAD | D34: N | E34: 44998 | F34: DESLIGAMENTO | G34: RUA RIO VERMELHO | H34: 755 | I34: SANTA MONICA | J34: FEIRA DE SANTANA | K34: 2º | L34: FUNDO DO POSTO CAJUEIRO | N34: (75)9-8152-7047
A35: .09366917 | B35: SONIA MARIA DE CARVALHO SOUZA | C35: MANPOWER | D35: 44756 | E35: 45019 | F35: DESLIGAMENTO | G35: RUA ARI BARROSO | H35: 334 | I35: SERRARIA BRASIL | J35: FEIRA DE SANTANA | K35: ADM | M35: REF: RODOVIARIA | N35: N
A36: 80152714 | B36: MARLUCIA DA CONCEIÇÃO LIMA | C36: PEPSICO | D36: 05/11/2018 | E36: 45021 | F36: DESLIGAMENTO | G36: RUA OPALA | H36: 46 | I36: BRASILIA | J36: FEIRA DE SANTANA | K36: 2º | L36: EM FRENTE MERCADINHO NOGUEIRA 2 | N36: N
A37: 80101499 | B37: ELANE SANTANA | C37: PEPSICO | D37: 12/02/2018 | E37: 45028 | F37: DESLIGAMENTO | G37: RESIDENCIAL ALTO DO ROSARIO BL | H37: 18 | I37: MANGABEIRA | J37: FEIRA DE SANTANA | K37: 2º
A38: 40287198 | B38: GILHERLON OLIVEIRA DE JESUS | C38: PEPSICO | D38: 01/12/2014 | E38: 45028 | F38: DESLIGAMENTO | G38: RUA MARIO PEREIRA FRANCO | H38: 97 | I38: SOBRADINHO | J38: FEIRA DE SANTANA | K38: 1º
A39: 80069244 | B39: CAILAN SILVA BARROS | C39: PEPSICO | D39: 17/07/2017 | E39: 45029 | F39: DESLIGAMENTO | G39: RUA CAMILO V COSTA | H39: N | I39: PAPAGAIO | J39: FEIRA DE SANTANA | K39: 2º | M39: EM FRENTE AO COND VILLE DUO
A40: 40185185 | B40: DENILLY SOUZA ALVES | C40: PEPSICO | D40: 16/01/2012 | E40: 45033 | F40: DESLIGAMENTO | G40: RUA MEDEIROS NETO | H40: N | I40: TOMBA | J40: FEIRA DE SANTANA | K40: ADM | M40: EM FRENTE AO COND: PARQUE DAS FILIPINAS | N40: N
B41: AGLAÉ SOUZA DO VALE SILVA | C41: RANDSTAD | E41: 45050 | F41: DESLIGAMENTO | G41: RUA ILHA BELA | H41: 25 | I41: PAPAGAIO | J41: FEIRA DE SANTANA | K41: 1º | L41: EM FRENTE AO IGREJA COMUNIDADE SÃO JOSÉ | N41: N
B42: CLEITON SILVA LIMA | C42: RANDSTAD | E42: 45050 | F42: DESLIGAMENTO | G42: RUA CONSELHEIRO PENA | H42: 751 | I42: PANORAMA | J42: FEIRA DE SANTANA | K42: 2º | N42: N
A43: 40185018 | B43: IAGGO ANDREY COSTA BARBOSA | C43: PEPSICO | D43: 16/01/2012 | E43: 45054 | F43: DESLIGAMENTO | G43: AV. RUA RUBENS FRANCISCO DIAS | H43: N | I43: PAPAGAIO | J43: FEIRA DE SANTANA | K43: 3º | M43: EM FRENTE AO CONDOMINIO CANADA HOUSES | N43: N
A44: 40185041 | B44: JOSÉ NILTON AMORIM AMORIM DOS SANTOS | C44: PEPSICO | D44: 16/01/2012 | E44: 45054 | F44: DESLIGAMENTO | G44: RESIDENCIAL AQUARIOS | H44: N | I44: AVIARIO ( RUA PRINCIPAL) | J44: FEIRA DE SANTANA | K44: 2º | N44: N
A45: 40216118 | B45: SARA MONIELLE DE OLIVEIRA ATAIDE | C45: PEPSICO | D45: 10/06/2013 | E45: 45085 | F45: DESLIGAMENTO | G45: RUA ITORORO - COND CENTRAL PARK | H45: N | I45: RUA NOVA | J45: FEIRA DE SANTANA | K45: 2º | M45: COND CENTRAL PARK | N45: N
A46: 40175816 | B46: MARIELLEN OLIVEIRA CALMON | C46: PEPSICO | D46: 01/08/2011 | E46: 45085 | F46: DESLIGAMENTO | G46: RUA RUBENS FRANCISCO DIAS | H46: 100 | I46: PAPAGAIO | J46: FEIRA DE SANTANA | K46: 2º | M46: EM FRENTE AO COND: AZZUL VILLE | N46: (75)9-9266-0247
B47: DANIELE DA CRUZ NASCIMENTO | C47: PEPSICO | E47: 45091 | F47: DESLIGAMENTO | G47: RUA RIBEIRO LOPES | I47: PAPAGAIO | J47: FEIRA DE SANTANA | K47: 1º | L47: CASA DA CARNE OLIVEIRA | M47: RESIDENCIAL ALTO DO PAPAGAIO - | N47: 75 9 9180-0920
A48: NA | B48: MICHELE SANTOS OLIVEIRA | C48: CWBEM | D48: N | E48: 45098 | F48: DESLIGAMENTO | G48: RUA ARTUR NEIVA | H48: 242 | I48: SÃO JOÃO | J48: FEIRA DE SANTANA | K48: 1º | L48: EM FRENTE AO REI DO PARA - CHOQUE | N48: N
A49: 80902033 | B49: CARLUENAN LUCENAS DE MENESES | C49: PEPSICO | D49: N | E49: 45117 | F49: REALOCAÇÃO | G49: TRAVE: CHÁCARA MIRINEU | H49: 520 | I49: SIM | J49: FEIRA DE SANTANA | K49: ADM | M49: EM FRENTE AO COND: VILA DE ESPENHA | N49: N
A50: 40277780 | B50: FÁBIO COSTA DA LUZ ABADE | C50: PEPSICO | D50: 16/06/2014 | E50: 45121 | F50: DESLIGAMENTO | G50: RUA AMANDA DE ASSIS COSTA | H50: AMELIA RODRIGUES | I50: 1º | J50: FEIRA DE SANTANA | K50: 2º | L50: EM FRENTE AO DEPOSITO ERICK
A51: 40277816 | B51: GLEDSON SILVA DE ALMEIDA | C51: PEPSICO | D51: 16/06/2014 | E51: 45140 | F51: DESLIGAMENTO | G51: RUA FELINTO MARQUES CERQUEIRA | H51: 1246 | I51: BRASILIA | J51: FEIRA DE SANTANA | K51: 2° | M51: EM FRENTE AO PETSHOP QUATRO PATAS | N51: N
A52: 40102418 | B52: MARCIO SOUZA ALVES | C52: PEPSICO | D52: 21/01/2004 | E52: 45153 | F52: MUDANÇA PARA VT | G52: AV: ARTEMIA PIRES | H52: N | I52: SIM | J52: FEIRA DE SANTANA | K52: ADM | M52: EM FRENTE AO COND: ARBOL RESIDENCE | N52: N
A53: NA | B53: CRISTINNA DE CASTRO BARROS | C53: RANDSTAD | D53: N | E53: N | F53: DESLIGAMENTO | G53: RUA MONSENHOR ADERBAL MIRANDA | H53: 199 | I53: SERRARIA BRASIL | J53: FEIRA DE SANTANA | K53: 2º | L53: SUPERMERCADO O PONTINHO | N53: N
A54: NA | B54: MARIA DIENI ASSIS SOUZA | C54: CWBEM | D54: N | E54: N | F54: DESLIGAMENTO | G54: RUA CASA BRANCA | H54: 65 | I54: CONCEIÇÃO II | J54: FEIRA DE SANTANA | K54: 2º | L54: POSTO DE SAUDE DA CONCEIÇÃO | N54: N
A55: NA | B55: THALLISON SOARES SOUZA | C55: RANDSTAD | D55: N | E55: N | F55: DESLIGAMENTO | G55: TRAV: LIMOEIRO | H55: 11 | I55: LIMOEIRO | J55: FEIRA DE SANTANA | K55: 2º | N55: N
A56: 80185932 | B56: LEIA DE SOUZA PACHECO | C56: PEPSICO | D56: 13/05/2019 | E56: N | F56: DESLIGAMENTO | G56: RUA FRANCISCO MARTINS DA SILVA | H56: 229 | I56: PONTO CENTRAL | J56: FEIRA DE SANTANA | K56: 2º | M56: PROX: MINISTERIO DO TRABALHO | N56: N
A57: 80152714 | B57: MARLUCIA DA CONCEIÇÃO LIMA | C57: PEPSICO | D57: 05/11/2018 | E57: N | F57: DESLIGAMENTO | G57: RUA OPALA | H57: 46 | I57: BRASILIA | J57: FEIRA DE SANTANA | K57: 2º | L57: EM FRENTE MERCADINHO NOGUEIRA 2 | N57: N
A58: 40182964 | B58: AILTON DOS SANTOS MOREIRA | C58: PEPSICO | D58: 14/11/2011 | E58: 45183 | F58: DESLIGAMENTO | G58: RUA JEOVÁ | H58: 110 | I58: HUMILDES | J58: FEIRA DE SANTANA | K58: 2º | M58: PROX. DA LOJA BOUTIQUE J.MM) | N58: N
A59: 40216309 | B59: JANILSON BACELAR DOS ANJOS | C59: PEPSICO | D59: 11/06/2013 | E59: 45183 | F59: DESLIGAMENTO | G59: ESTRADA DA SALGADEIRA | H59: N | I59: HUMILDES | J59: FEIRA DE SANTANA | K59: 2º | L59: IGREJA DA ROCINHA | N59: N
A60: 80014738 | B60: LUIZ CARLOS LIMA DE JESUS | C60: PEPSICO | D60: 04/04/2016 | E60: 45183 | F60: DESLIGAMENTO | G60: RUA CASCALHEIRA | H60: 514 | I60: PEDRA DO DESCANÇO | J60: FEIRA DE SANTANA | K60: 2º | M60: EM FRENTE AO GALETO NA BRASA | N60: N
A61: 80015639 | B61: TARCISIO ROCHA SANTOS | C61: PEPSICO | D61: 11/04/2016 | E61: 44818 | F61: DESLIGAMENTO | G61: RUA ANTONIO RIBEIRO MARQUES | H61: N | I61: JARDIM BRASIL | J61: FEIRA DE SANTANA | K61: ADM | M61: EM FRENTE AO COND. RESERVA PARATI | N61: N
A62: NA | B62: ELIELSON SANTOS FERREIRA | C62: PEPSICO | D62: N | E62: 45183 | F62: DESLIGAMENTO | G62: RUA SANTO ANTONIO | H62: 52 | I62: TOMBA | J62: FEIRA DE SANTANA | K62: 1º | M62: PROX: AO MERCADO TODO DIA | N62: (75)9 8266 - 3327
A63: 80144095 | B63: VIVIANE CERQUEIRA DE JESUS SANTOS CARVALHO | C63: PEPSICO | D63: 10/09/2018 | E63: 45183 | F63: DESLIGAMENTO | G63: RUA SÃO MIGUEL DO MAR | H63: 115 | I63: SANTAN MONICA II | J63: FEIRA DE SANTANA | K63: 1º | M63: NO FUNDO DA CONFIANÇA EXTINTOR. | N63: N
A64: 80220140 | B64: ANDERSON FERREIRA CHAGAS | C64: PEPSICO | D64: 04/11/2019 | E64: 45183 | F64: DESLIGAMENTO | G64: AV. IGUATEMI COND FIGUEIRAS | H64: N | I64: MANGABEIRA | J64: FEIRA DE SANTANA | K64: AMD EPC | N64: N
B65: AGLAÉ SOUZA DO VALE SILVA | C65: RANDSTAD | D65: N | E65: 45139 | F65: DESLIGAMENTO | G65: RUA ILHA BELA | H65: 25 | I65: PAPAGAIO | J65: FEIRA DE SANTANA | K65: 1º | L65: EM FRENTE AO IGREJA COMUNIDADE SÃO JOSÉ | N65: N
B66: GIVANILDES DOS SANTOS | C66: RANDSTAD | E66: 45139 | F66: DESLIGAMENTO | G66: RUA PEDRO SUZARTE | H66: 1538 | I66: BRASILIA | J66: FEIRA DE SANTANA | K66: 2º | L66: MERCADONHO DAVI | N66: 9 8265 - 7095
B67: OTAVIO MACHADO DE OLIVEIRA JUNIOR | C67: RANDSTAD | E67: 45139 | F67: DESLIGAMENTO | G67: TRAV: CHÁCARA MIRINEU | H67: 520 | I67: SANTO ANTONIO DOS PRAZERES | J67: FEIRA DE SANTANA | K67: 2º | L67: FRENTE AO COND: VILA DE ESPENHA | N67: N
B68: SANDRA OLIVEIRA DA SILVA PINTO | C68: RANDSTAD | E68: 45139 | F68: DESLIGAMENTO | G68: VIA LOCAL A | H68: 32 | I68: EXPANSÃO FEIRA IX | J68: FEIRA DE SANTANA | K68: 1º | L68: FINAL DE LINHA DO EXPANSÃO DO FEIRA IX | N68: N
B69: SILVANA MATOS SILVA LEITE | C69: RANDSTAD | E69: 45139 | F69: DESLIGAMENTO | G69: RUA ASSIS | H69: 140 | I69: ASA BRANCA | J69: FEIRA DE SANTANA | K69: 2º | L69: PROX: A IGREJA UNIVERSAL | M69: PROX: A IGREJA UNIVERSAL | N69: 9 9863 - 5509
A70: 80867673 | B70: ANDRESSA DE OLIVEIRA CERQUEIRA | C70: PEPSICO | D70: 06/09/2021 | E70: 45194 | F70: NÃO UTILIZA O ROTEIRO | G70: RUA RIO TIJUCA | H70: 52 | I70: BRASILIA | J70: FEIRA DE SANTANA | K70: 2º | L70: EM FRENTE AO RESIDENCIAL ALAMEDA DA TIJUCA 1 | N70: N
A71: 40172746 | B71: ANDERSON DE JESUS AMARAL | C71: PEPSICO | D71: 02/05/2011 | E71: 45244 | F71: DESLIGAMENTO | G71: OLHOS D´AGUA | H71: FEIRA DE SANTANA | I71: 3º | K71: EM FRENTE AFAS | L71: N
A72: 81035813 | B72: RANIERE ROSEMBERG SOUZA DOS SANTOS | C72: PEPSICO | D72: N | E72: 45234 | F72: DESLIGAMENTO | G72: RUA G, CAMINHO 13 | I72: FEIRA X | J72: FEIRA DE SANTANA | N72: 74 9 9814-3201
A73: 40216296 | B73: JOSELMA LEÃO COSTA | C73: PEPSICO | D73: 10/06/2013 | E73: 45234 | F73: DESLIGAMENTO | G73: AVENIDA BAHIA | H73: 246 | I73: QUEIMADINHA | J73: FEIRA DE SANTANA | K73: 1º | L73: AV: BAHIA | M73: PROX : A IGREJA DE TODOS OS SANTOS | N73: N
A74: 80997389 | B74: ROSANGELA BARRETO TEIXEIRA | C74: PEPSICO | D74: N | E74: 45234 | F74: DESLIGAMENTO | G74: CAM: 02 | H74: 6 | I74: FEIXA V | J74: FEIRA DE SANTANA | K74: 2º | M74: PROX: A FARMACIA BRITO | N74: (75)9-8238-9247
A75: 40216130 | B75: FRANCISCO ALMEIDA SOUZA NETO | C75: PEPSICO | D75: 10/06/2013 | E75: 45234 | F75: DESLIGAMENTO | G75: RUA ALEXANDRE FLAMINGO | H75: N | I75: GABRIELA | J75: FEIRA DE SANTANA | K75: 3º | M75: EM FRENTE A IGREJA EVANGELICA | N75: N
A76: NA | B76: LAILA FERREIRA DA SILVA | C76: CWBEM | D76: 45099 | E76: 45279 | F76: DESLIGAMENTO | G76: RUA GOIÁS | H76: 17 | I76: JARDIM ACÁCIA | J76: FEIRA DE SANTANA | K76: 1º | L76: PROX: A PADARIA DE IRMÃ ROSA | N76: 75 9 8189 - 3112
A77: 81009963 | B77: ELIAS BATISTA DOS SANTOS | C77: PEPSICO | D77: 44928 | E77: 45293 | F77: DESLIGAMENTO | G77: RUA GÊMEOS | H77: 135 | I77: TOMBA | J77: FEIRA DE SANTANA | K77: 3º | L77: AO LADO DA IGREJA ADVENTISTA | N77: 71991958233
A78: 40192143 | B78: ROBERTO LEAL CARDOSO RAMOS | C78: PEPSICO | D78: 41096 | E78: 45293 | F78: DESLIGAMENTO | G78: RUA TEREZINHA MAGALHÃES | H78: N | I78: FRATERNIDADE | J78: FEIRA DE SANTANA | K78: 2º | L78: BAR DA KAISER DRINK´S | N78: N
A79: 80066813 | B79: ANA JULIA DE JESUS | C79: PEPSICO | D79: 44095 | E79: 45327 | F79: DESLIGAMENTO | G79: CAMINHO QUINZE | H79: 5 | I79: CAMPO LIMPO | J79: FEIRA DE SANTANA | K79: 1º | M79: EM FRENTE A IGREJA DA FÉ EM JESUS CRISTO | N79: N
A80: 81066196 | B80: CAROLINE SAMPAIO DE SOUZA | C80: PEPSICO | D80: N | E80: 45327 | F80: DESLIGAMENTO | G80: GABRIELA | I80: 2º | J80: FEIRA DE SANTANA | N80: 9 9126 - 2926
A81: 80851930 | B81: DANILO OLIVEIRA MENDES | C81: PEPSICO | D81: N | E81: 45419 | F81: DESLIGAMENTO | G81: MERCADINHO MARINHO ( AO LADO DA CASA ) | I81: FEIRA X | J81: FEIRA DE SANTANA | L81: N | N81: N
A82: 80315518 | B82: RODRIGO ASSUNCAO NEVES | C82: PEPSICO | D82: 15/02/2021 | E82: 45419 | F82: DESLIGAMENTO | G82: AO LADO DA FABRICA DE IOGURT BIZZ | I82: PANORAMA | J82: FEIRA DE SANTANA | L82: N | N82: N
A83: 81018416 | B83: BARBARA PINTO DE SOUZA | C83: PEPSICO | D83: N | E83: 45419 | F83: DESLIGAMENTO | G83: RUA DAS ROSAS | H83: 176 | I83: BRASILIA | J83: FEIRA DE SANTANA | N83: 98183-2194
A84: 81016149 | B84: SIMARA SILVA BATISTA | C84: PEPSICO | D84: 44958 | E84: N | F84: DESLIGAMENTO | G84: EM FRENTE AO RESIDENCIAL SANTANA LIFE | I84: PEDRA DO DESCANÇO | J84: FEIRA DE SANTANA | K84: 1º | N84: 9 9862 - 4038
A85: 81010996 | B85: MARIO DE JESUS SANTANA | C85: PEPSICO | D85: 44935 | E85: 45553 | F85: DESLIGAMENTO | G85: RUA HONORATO BONFIM | H85: 496 | I85: BRASILIA | J85: FRENTE AO BISCOITOS ITÁLIA | M85: FRENTE AO BISCOITOS ITÁLIA | N85: 9 8114 - 7924
A86: 80122249 | B86: SORAYA ALVES BATISTA | C86: PEPSICO | D86: 04/06/2018 | E86: N | F86: NÃO UTILIZA O ROTEIRO | G86: RUA CORREDOR DOS ARAÇAS | H86: 650 | I86: SIM | J86: FEIRA DE SANTANA | K86: ADM | M86: EM FRENTE AO COND: SELLETO | N86: (73)9-9135-0503
A87: 40190451 | B87: FABIO PINTO DOS SANTOS | C87: PEPSICO | D87: 17/05/2012 | E87: N | F87: DESLIGAMENTO | G87: RUA CARMO DF MINAS | H87: 284 | I87: CONCEIÇÃO | J87: FEIRA DE SANTANA | K87: 1º | L87: NA ESQUINA DA RUA CARMO DE MINAS | N87: N
A88: 40192612 | B88: JAIRO RODRIGUES NEPOMUCENO | C88: PEPSICO | D88: 12/07/2012 | E88: N | F88: AFASTAMENTO | G88: RUA A, CAMINHO C 3 | H88: N | I88: FEIRA X | J88: FEIRA DE SANTANA | K88: 1º | L88: ESPAÇO TERAPÊUTICO CASA DE MAINHA | N88: N
A89: 80186544 | B89: MARIA FLAVIA COSTA CRUZ | C89: PEPSICO | D89: 20/05/2019 | E89: N | F89: DESLIGAMENTO | G89: RUA CARMO DF MINAS | H89: 284 | I89: CONCEIÇÃO | J89: FEIRA DE SANTANA | K89: 1º | L89: NA ESQUINA DA RUA CARMO DE MINAS | N89: N
A90: 80011644 | B90: MATHEUS DE OLIVEIRA MELO | C90: PEPSICO | D90: 18/01/2016 | E90: N | F90: AFASTAMENTO | G90: RUA E | H90: N | I90: FEIRA X | J90: FEIRA DE SANTANA | K90: 1º | M90: EM FRENTE A LOJA MODA PAULISTA | N90: N
A91: 40192613 | B91: REGIS RAMOS DE MORAIS | C91: PEPSICO | D91: 12/07/2012 | E91: N | F91: AFASTAMENTO | G91: AVENIDA DOIS CAMINHO | H91: N | I91: CONJ.FEIRA VII | J91: FEIRA DE SANTANA | K91: 1º | M91: EM FRENTE AO MERCADINHO SANTANA | N91: N
A92: 40172746 | B92: ANDERSON DE JESUS AMARAL | C92: PEPSICO | D92: 02/05/2011 | E92: N | F92: NÃO UTILIZA O ROTEIRO | G92: R. SENADOR QUINTINO, | H92: 792 | I92: OLHOS D´AGUA | J92: FEIRA DE SANTANA | K92: 3º | M92: EM FRENTE AFAS | N92: N
A93: NA | B93: MARCELA BARBOSA PEREIRA DE JESUS | C93: CWBEM | D93: 45098 | E93: 45581 | F93: DESLIGAMENTO | G93: RUA SÃO PEDRO DOS FERROS | H93: 7 | I93: SIM | J93: FEIRA DE SANTANA | K93: 2º | N93: 75 9 8142 - 7843
A94: NA | B94: TALITA DE JESUS SANTOS | C94: CWBEM | D94: 45450 | E94: 45605 | F94: DESLIGAMENTO | G94: RUA SÃO RAIMUNDO DO MERITI | H94: 245 | I94: CAMPO LIMPO | J94: FEIRA DE SANTANA | K94: 2º | L94: FEIRA DE SANTANA | M94: CASA DE AZULEJOS BRANCO, PRÓXIMO AO QUISQUE | N94: 75982734513
A95: NA | B95: FILIPE FERREIRA RAMOS | C95: MANPOWER | D95: NA | E95: 45653 | F95: DESLIGAMENTO | G95: 45538 | H95: =I95 & ", " & J95 & ", " & K95 & ", " & L95 & ", BAHIA" & ", BRASIL" -> RUA ITACARAMBI, 46, FEIRA X, FEIRA DE SANTANA, BAHIA, BRASIL | I95: RUA ITACARAMBI | J95: 46 | K95: FEIRA X | L95: FEIRA DE SANTANA | M95: 1° T
A96: =_xlfn.XLOOKUP(B96,RH!E83:E207,RH!D83:D207,"NA") -> NA | B96: NADJANARA SANTANA LOPES | C96: PEPSICO | D96: 18/04/2022 | E96: 45757 | F96: DESLIGAMENTO | G96: =H96 & ", " & I96 & ", " & J96 & ", " & K96 & ", BAHIA" & ", BRASIL" -> TRAVENIDA E CHACARA MIRINEU, 520, SIM, FEIRA DE SANTANA, BAHIA, BRASIL | H96: TRAVENIDA E CHACARA MIRINEU | I96: 520 | J96: SIM | K96: FEIRA DE SANTANA | L96: ADM | N96: CONDOMINIO VILA DE ESPANHA

Sheet MOTORISTAS
B2: MOTORISTAS
B3: MOTORISTA | C3: CNH | D3: DATA EXP. | E3: DATA VAL. | F3: EXAME TOXICOLÓGICO | G3: CURSO DETRAN | H3: DOCUMENTO ASO
B4: HUDSON BARBOSA DE ARAUJO PEREIRA | C4: 3014420403 | D4: 37854 | E4: 45986 | F4: 45965 | G4: EAR | H4: OK
B5: OSMAN MIRANDA DA CRUZ | C5: 2182335135 | D5: 32569 | E5: 45978 | F5: 45943 | G5: EAR | H5: OK
B6: SIDNEY MIRANDA OLIVEIRA | C6: 3918018860 | D6: 44930 | E6: 48568 | F6: 45840 | G6: EAR | H6: OK
B7: LIDIVAL DIAS FREITAS | C7: 2623670313 | D7: 44838 | E7: 46635 | F7: 45748 | G7: EAR | H7: OK
B8: EDNALDO DO CARMO LOPES | C8: 1599930667 | D8: 44470 | E8: 48099 | F8: 45798 | G8: EAR | H8: N/A
B9: OTAVIO OLIVEIRA DO VALE | C9: 3958218521 | D9: 44494 | E9: 48124 | F9: 46134 | G9: EAR | H9: N/A
B10: ANGELO MARIO DOS SANTOS | C10: 4753813680 | D10: 44848 | E10: 48497 | F10: 45930 | G10: EAR | H10: N/A
B11: ROQUE DE JESUS ALMEIDA | C11: 1680405910 | D11: 44312 | E11: 45971 | F11: 45996 | G11: EAR | H11: N/A
B12: SANDRO JOSE FERREIRA DE FREITAS | C12: 4235721929 | D12: 42783 | E12: 45998 | F12: 46198 | G12: EAR | H12: N/A
B13: WALMIR DA CONCEIÇÃO RIBEIRO | C13: 593945360 | D13: 44875 | E13: 46700 | F13: 46196 | G13: EAR | H13: N/A
B14: GENIVALDO DE LIMA DE JESUS | C14: 4640872562 | D14: 39945 | E14: 47995 | F14: 46267 | G14: EAR | H14: N/A
B15: BRUNNO ANDERSON DA SILVA LEAL | C15: 882951029 | D15: 45589 | E15: 49202 | F15: 46196 | G15: EAR | H15: N/A
B16: SIDNEY ALVES DOS SANTOS | C16: 5465086442 | D16: 45345 | E16: 45986 | F16: N/A | G16: N/A | H16: N/A
B17: JOÃO EVANGELISTA RIBEIRO MORAIS | C17: 1417930017 | D17: 45202 | E17: 46291 | F17: N/A | G17: N/A | H17: N/A
B18: HUMBERTO SAMPAIO DE MACEDO | C18: 4962815875 | D18: 31596 | E18: 45886 | F18: N/A | G18: N/A | H18: N/A
B19: IANEY SANTOS MOREIRA | C19: 3398002008 | D19: 38094 | E19: 49087 | F19: N/A | G19: N/A | H19: N/A
B20: JOÃO VICTOR MATOS SILVA | C20: 7567858820 | D20: 45863 | E20: 45862 | F20: N/A | G20: N/A | H20: N/A
B21: JUCELIA SANTOS DA SILVA | C21: 2583278938 | D21: 44770 | E21: 46593 | F21: N/A | G21: N/A | H21: N/A
B22: UBIRAJARA FRANÇA | C22: 1179007984 | D22: 45043 | E22: 46826 | F22: N/A | G22: N/A | H22: N/A
B23: JADSON BORGES DA SILVA SANTOS | C23: 4549270300 | D23: 44671 | E23: 48303 | F23: N/A | G23: N/A | H23: N/A
B24: ANTONIO PAULO DA SILVA | C24: 5076466597 | D24: 44460 | E24: 46279 | F24: N/A | G24: N/A | H24: N/A
B25: HENRIQUE MENDES DA SILVA | C25: 2302730187 | D25: 44763 | E25: 46588 | F25: N/A | G25: N/A | H25: N/A
B26: FABIANO SILVA DE JESUS | C26: 5526518246 | D26: 45287 | E26: 48918 | F26: N/A | G26: N/A | H26: N/A

Sheet VEÍCULOS
B2: VEÍCULOS
B3: PLACA | C3: DOCUMENTO VEICULO (CRLV) | D3: LICENCIADO | E3: DATA VALIDADE | F3: CONOTACOGRAFO
B4: SKB4C99 | C4: 244079612187 | D4: 2025 | E4: 45961 | F4: 0011065641
B5: SKE6J24 | C5: 244110292140 | D5: 2025 | E5: 45961 | F5: 0011154537
B6: SKG2H53 | C6: 244145005511 | D6: 2025 | E6: 45961 | F6: P23488955
B7: SKG3F12 | C7: 244145004680 | D7: 2025 | E7: 45961 | F7: P23427834
B8: SKG4G65 | C8: 244139120290 | D8: 2025 | E8: 45961 | F8: P23471388
B9: SKG4J37 | C9: 244145006186 | D9: 2025 | E9: 45961 | F9: P23489735
B10: QTW6B54 | C10: 01218946501 | D10: 2025 | E10: 45900 | F10: P23489273
B11: NZI6F44 | C11: 233697016830 | D11: 2025 | E11: 45869 | F11: P23466564
B12: PJW3313 | C12: 01083690873 | D12: 2025 | E12: 31/02/2025 | F12: 0010770653
B13: OLF0D24 | C13: 213197176260 | D13: 2025 | E13: 31/06/2025 | F13: 0010061759
B14: PKS1I39 | C14: 213148020812 | D14: 2025 | E14: 45900 | F14: N/A
B15: OZR7B70 | C15: 223391674806 | D15: 2025 | E15: 31/09/2025 | F15: N/A
B16: PLS1E39 | C16: 223498874322 | D16: 2025 | E16: 45900 | F16: N/A
B17: PJO3A80 | C17: 244004094984 | D17: 2025 | E17: 45808 | F17: N/A
B18: SKJ7D62 | C18: 244181377660 | D18: 2025 | E18: 45930 | F18: N/A
B19: OLD1G02 | C19: 223564347941 | D19: 2025 | E19: 45899 | F19: N/A
B20: PBK8F68 | C20: 233891694377 | D20: 2025 | E20: 30/02/2025 | F20: N/A
B21: OZV7973 | C21: 243961457786 | D21: 2024 | E21: 45898 | F21: N/A

Sheet VEICULOS E MOTORISTAS ATIVOS
B2: VEÍCULO | C2: MOTORISTAS ATUAIS ROTEIROS PEPSICO | D2: CNH | E2: TOXICOLÓGICO | F2: CURSO DETRAN | G2: ASO | H2: ROTA | I2: TURNO
B3: OZV7973 | C3: JADSON BORGES DA SILVA SANTOS | D3: 4549270300 | E3: N/A | F3: N/A | G3: N/A | H3: 1 | I3: 1° | K3: QUANTIDADE DE MOTORISTAS
B4: OZR7B70 | C4: BRUNNO ANDERSON DA SILVA LEAL | D4: 882951029 | E4: 46196 | F4: EAR | G4: N/A | H4: 1 | I4: 1° | K4: 1 TURNO | L4: 2 TURNO | M4: 3 TURNO | N4: ADM
B5: RDI2F74 | C5: ANTONIO PAULO DA SILVA | D5: 5076466597 | E5: N/A | F5: N/A | G5: N/A | H5: 2 | I5: 1° | K5: 14 | L5: 10 | M5: 5 | N5: 3
B6: SKB4C99 | C6: HUDSON BARBOSA DE ARAUJO PEREIRA | D6: 3014420403 | E6: N/A | F6: N/A | G6: OK | H6: 3 | I6: 1° | M6: TOTAL= | N6: =SUM(K5:N5) -> 32
B7: OLF0D24 | C7: WALMIR DA CONCEIÇÃO RIBEIRO | D7: 593945360 | E7: 46196 | F7: EAR | G7: N/A | H7: 4 | I7: 1°
B8: SKE6J24 | C8: OSMAN MIRANDA DA CRUZ | D8: 2182335135 | E8: N/A | F8: N/A | G8: OK | H8: 5 | I8: 1°
B9: PSF8G68 | C9: EDNALDO DO CARMO LOPES | D9: 1599930667 | E9: 45798 | F9: EAR | G9: N/A | H9: 5 | I9: 1°
B10: SKG2H53 | C10: LIDIVAL DIAS FREITAS | D10: 2623670313 | E10: N/A | F10: N/A | G10: OK | H10: 6 | I10: 1°
B11: OXU9218 | C11: ANGELO MARIO DOS SANTOS | D11: 4753813680 | E11: 45930 | F11: EAR | G11: N/A | H11: 6 | I11: 1°
B12: OZR7B70 | C12: JOÃO EVANGELISTA RIBEIRO MORAIS | D12: 1417930017 | E12: N/A | F12: N/A | G12: N/A | H12: 7 | I12: 1°
B13: SKG3F12 | C13: SIDNEY MIRANDA OLIVEIRA | D13: 3918018860 | E13: N/A | F13: N/A | G13: OK | H13: 8 | I13: 1°
B14: KRR9A92 | C14: FABIANO SILVA DE JESUS | D14: 5526518246 | E14: N/A | F14: N/A | G14: N/A | H14: 8 | I14: 1°
B15: PKS1I39 | C15: SIDNEY ALVES DOS SANTOS | D15: 5465086442 | E15: N/A | F15: N/A | G15: N/A | H15: 9 | I15: 1°
B16: PLS1E39 | C16: HUMBERTO SAMPAIO DE MACEDO | D16: 4962815875 | E16: N/A | F16: N/A | G16: N/A | H16: 9 | I16: 1°
B17: QTW6C71 | C17: HENRIQUE MENDES DA SILVA | D17: 2302730187 | E17: N/A | F17: N/A | G17: N/A | H17: 1 | I17: ADM
B18: OLD1G02 | C18: JUCELIA SANTOS DA SILVA | D18: 2583278938 | E18: N/A | F18: N/A | G18: N/A | H18: 2 | I18: ADM
B19: OZR7B70 | C19: JOÃO EVANGELISTA RIBEIRO MORAIS | D19: 1417930017 | E19: N/A | F19: N/A | G19: N/A | H19: 3 | I19: ADM
B20: QTW6B54 | C20: SANDRO JOSE FERREIRA DE FREITAS | D20: 4235721929 | E20: 46198 | F20: EAR | G20: N/A | H20: 1 | I20: 2°
B21: PJO3A80 | C21: IANEY SANTOS MOREIRA | D21: 3398002008 | E21: N/A | F21: N/A | G21: N/A | H21: 1 | I21: 2°
B22: SKJ7D62 | C22: JOÃO VICTOR MATOS SILVA | D22: 7567858820 | E22: N/A | F22: N/A | G22: NA/ | H22: 1 | I22: 2°
B23: PXO7I32 | C23: ROQUE DE JESUS ALMEIDA | D23: 1680405910 | E23: 45996 | F23: EAR | G23: N/A | H23: 2 | I23: 2°
B24: OWN4J49 | C24: OTAVIO OLIVEIRA DO VALE | D24: 3958218521 | E24: 46134 | F24: EAR | G24: N/A | H24: 2 | I24: 2°
B25: PJW3313 | C25: GENIVALDO DE LIMA DE JESUS | D25: 4640872562 | E25: 46267 | F25: EAR | G25: N/A | H25: 3 | I25: 2°
B26: PBK8F68 | C26: UBIRAJARA FRANÇA | D26: 1179007984 | E26: N/A | F26: N/A | G26: NA/ | H26: 3 | I26: 2°
B27: OLD1G02 | C27: JUCELIA SANTOS DA SILVA | D27: 2583278938 | E27: N/A | F27: N/A | G27: N/A | H27: 4 | I27: 2°
B28: PLS1E39 | C28: HUMBERTO SAMPAIO DE MACEDO | D28: 4962815875 | E28: N/A | F28: N/A | G28: N/A | H28: 5 | I28: 2°
B29: OZV7973 | C29: JADSON BORGES DA SILVA SANTOS | D29: 4549270300 | E29: N/A | F29: N/A | G29: N/A | H29: 5 | I29: 2°
B30: SKB4C99 | C30: HUDSON BARBOSA DE ARAUJO PEREIRA | D30: 3014420403 | E30: N/A | F30: N/A | G30: OK | H30: 1 | I30: 3°
B31: SKE6J24 | C31: OSMAN MIRANDA DA CRUZ | D31: 2182335135 | E31: N/A | F31: N/A | G31: OK | H31: 1 | I31: 3°
B32: SKG2H53 | C32: LIDIVAL DIAS FREITAS | D32: 2623670313 | E32: N/A | F32: N/A | G32: OK | H32: 2 | I32: 3°
B33: RDI2F74 | C33: ANTONIO PAULO DA SILVA | D33: 5076466597 | E33: N/A | F33: N/A | G33: N/A | H33: 2 | I33: 3°
B34: OZR7B70 | C34: JOÃO EVANGELISTA RIBEIRO MORAIS | D34: 1417930017 | E34: N/A | F34: N/A | G34: N/A | H34: 2 | I34: 3°

Sheet DOCUMENTOS AZZAF
B2: DOCUMENTOS AZZAF
B3: AGERBA CADASTRAL | C3: CERTIDÃO FEDERATIVA | D3: CERTIDÃO MUNICIPAL | E3: CERTIFICADO CADASTUR
B4: 0901.2023/006399 | C4: F72E.CA03.167B.4DE2 | D4: 52.065-9 | E4: 17.304.967/0001-60

Sheet Planilha1
A2: CARGO | B2: DESCCCUSTO | C2: Contagem de NOME
A3: ALMOXARIFE | B3: ALMOXARIFADO PECAS | C3: 1
A4: ANALISTA CONTROLADORIA PL | B4: CONTR FABR ITU MOH | C4: 1
A5: ANALISTA DE MELHORIA CONTINUA SR | B5: ATB & LSS MANUF PROD | C5: 1
A6: ANALISTA DE PCM PL | B6: GERENCIA MANUTENCAO | C6: 1
A7: ANALISTA DE QUALIDADE JR | B7: QUALIDADE CHOCOLATE | C7: 2
A8: ANALISTA DE QUALIDADE PL | B8: QUALIDADECENTRAL CO | C8: 1
A9: ASSISTENTE LOGISTICA SR | B9: ALM INSUMOS BA | C9: 2
B10: EXP E ARMAZENS FOODS | C10: 4
A11: AUXILIAR DE PRODUCAO | B11: COMBI 24000 | C11: 16
B12: PREPARACAO ESTERELIZ | C12: 10
B13: PRODUCAO MAGICO BA | C13: 5
B14: PRODUCAO MISTURA BA | C14: 1
B15: PRODUCAO TODDY BA | C15: 4
A16: COORDENADOR DE QUALIDADE | B16: QUALIDADE CHOCOLATE | C16: 1
A17: COORDENADOR DE UTILIDADES | B17: GERENCIA MANUTENCAO | C17: 1
A18: ENGENHEIRO PL | B18: GERENCIA MANUTENCAO | C18: 1
A19: GERENTE DE MANUFATURA | B19: GERENCIA PRODUCAO BA | C19: 1
B20: GERENTE DE PLANTA BA | C20: 1
A21: GERENTE DISTRIBUICAO | B21: EXP E ARMAZENS FOODS | C21: 1
A22: GERENTE MANUTENCAO | B22: GERENCIA MANUTENCAO | C22: 1
A23: OPERADOR MULTIFUNCIONAL | B23: COMBI 24000 | C23: 15
B24: PREPARACAO ESTERELIZ | C24: 5
B25: PRODUCAO MAGICO BA | C25: 4
B26: PRODUCAO MISTURA BA | C26: 3
B27: PRODUCAO TODDY BA | C27: 3
A28: OPERADOR MULTIFUNCIONAL ESPECIALIZADO | B28: GERENCIA PRODUCAO BA | C28: 1
B29: PREPARACAO ESTERELIZ | C29: 1
A30: OPERADOR UTILIDADES | B30: MANUTENCAO UTILIDADE | C30: 4
A31: SUPERVISOR DE DISTRIBUICAO A | B31: EXP E ARMAZENS FOODS | C31: 1
A32: SUPERVISOR DE QUALIDADE | B32: QUALIDADE CHOCOLATE | C32: 1
A33: TECNICO DE QUALIDADE I | B33: QUALIDADE CHOCOLATE | C33: 6
A34: TECNICO ELETROMECANICO II | B34: GERENCIA MANUTENCAO | C34: 7
A35: TECNICO ESPECIALISTA | B35: GERENCIA MANUTENCAO | C35: 2
A36: TECNICO MECANICO II | B36: GERENCIA MANUTENCAO | C36: 3
A37: TECNICO MECANICO III | B37: GERENCIA MANUTENCAO | C37: 1
A38: TECNICO SEGURANCA DO TRABALHO II | B38: SEG TRAB ENFERMAGEM | C38: 2
A39: Total Geral | C39: 115

Sheet Planilha2
A2: GPID | B2: EMPRESA
A3: Terceiro | B3: CWBEM
B4: LIMGER
B5: MANPOWER
B6: PEPSICO
A7: Terceiro Total
A8: Total Geral
